Workbook
Name ChartWAFCost: OFFSET(INDEX(Dashboard!$H$51:$M$122,1,1),0, 3, COUNTA(Dashboard!$H$51:$H$122),1)
Name ChartWAFLabels: OFFSET(INDEX(Dashboard!$H$51:$M$122,1,1),0, 0, COUNTA(Dashboard!$H$51:$H$122),1)
Name ChartWAFOps: OFFSET(INDEX(Dashboard!$H$51:$M$122,1,1),0, 4, COUNTA(Dashboard!$H$51:$H$122),1)
Name ChartWAFPerf: OFFSET(INDEX(Dashboard!$H$51:$M$122,1,1),0, 5, COUNTA(Dashboard!$H$51:$H$122),1)
Name ChartWAFRel: OFFSET(INDEX(Dashboard!$H$51:$M$122,1,1),0, 1, COUNTA(Dashboard!$H$51:$H$122),1)
Name ChartWAFSec: OFFSET(INDEX(Dashboard!$H$51:$M$122,1,1),0, 2, COUNTA(Dashboard!$H$51:$H$122),1)

Sheet Checklist
J1: Please send us feedback about the review checklists!
F2: Azure Review Checklist | H2: AI Landing Zone | I2: English | J2: ç Select a technology and a language ç
F3: Should anonymous telemetry data be collected (checklist name and language, no user input) for statistics? | T3: Version
F4: Yes | G4: Source: | H4: =Values!B2 -> Not verified | I4: =Values!J2 -> This check has not been looked at yet | T4: v1.5.4
G5: Review checklists | H5: =Values!B3 -> Open | I5: =Values!J3 -> There is an action item associated to this check
A6: AI Landing Zone | H6: =Values!B4 -> Fulfilled | I6: =Values!J4 -> This check has been verified, and there are no further action items associated to it | P6: Share GUID:
A7: Preview | B7: WAF: | C7: all | H7: =Values!B5 -> Not required | I7: =Values!J5 -> Recommendation understood, but not needed by current requirements
A8: Timestamp: | B8: 45763 | H8: =Values!B6 -> N/A | I8: =Values!J6 -> Not applicable for current design | P8: =Dashboard!$E$51 -> 1 | Q8: =Dashboard!$E$52 -> 1 | R8: =Dashboard!$E$53 -> 1 | S8: =Dashboard!$E$54 -> 1 | T8: =Dashboard!$E$55 -> 1
A9: ID | B9: Design Area | C9: Sub Area | D9: WAF Pillar | E9: Service | F9: Checklist item | G9: Description (optional) | H9: Severity | I9: Status | J9: Comment | K9: AMMP | L9: More info | M9: Training | N9: Graph Query | O9: GUID | P9: Secure | Q9: Cost | R9: Scale | S9: Simple | T9: HA | U9: Source File
A10: AI.1 | B10: Application Deployment | C10: Data Classification | D10: Operations | E10: Azure DevOps | F10: Establish a version control process for grounding data, for example, in RAG. | H10: Low | I10: Fulfilled | J10: Each update to /data folder will trigger data pipeline | O10: 20a734fb-ca83-4ce0-b3a7-935a00b2e9b9
A11: AI.10 | B11: BC and DR | C11: Quotas | D11: Reliability | E11: Azure OpenAI | F11: Ensure having adequate quotas of TPM & RPM for the workload | H11: Medium | I11: Fulfilled | J11: TPM & RPM setup for hackathon env | L11: More info | O11: 5ca44e46-85e2-4223-ace8-bb12308ca5f1
A12: AI.100 | B12: Identity and Access Management | C12: Authentication | D12: Security | E12: Microsoft Entra | F12: Use Microsoft Entra ID PIM access reviews to periodically validate resource entitlements. | H12: High | I12: Fulfilled | L12: More info | O12: c51df970-509c-4110-960a-601dd2348dbf
A13: AI.101 | B13: Identity and Access Management | C13: Authentication | D13: Security | E13: Azure API Management | F13: Require clients to authenticate using Entra ID when accessing AI model endpoints. | H13: High | I13: Fulfilled | L13: More info | O13: 21f656e3-7ba4-4d23-be79-02a6264a1942
A14: AI.102 | B14: Identity and Access Management | C14: Entra ID based access | D14: Security | E14: Azure OpenAI | F14: Key access (local authentication) is recommended to be disabled for security. After disabling key based access, Microsoft Entra ID becomes the only access method, which allows maintaining minimum privilege principle and granular control. | H14: High | I14: Fulfilled | J14: Result undefined: /subscriptions/6cb4dbdc-453c-4b5c-9a44-0fb71f3c6d7c/resourceGroups/ADWFab/providers/Microsoft.CognitiveServices/accounts/adwdemo3397848743 0 Result undefined: /subscriptions/6cb4dbdc-453c-4b5c-9a44-0fb71f3c6d7c/resourceGroups/ADWFab/providers/Microsoft.CognitiveServices/accounts/adwembed 0 Result undefined: /subscriptions/6cb4dbdc-453c-4b5c-9a44-0fb71f3c6d7c/resourceGroups/ADWFab/providers/Microsoft.Search/searchServices/aidwfab 0 Result undefined: /subscriptions/6cb4dbdc-453c-4b5c-9a44-0fb71f3c6d7c/resourceGroups/foundrygenaiops/providers/Microsoft.CognitiveServices/accounts/ai-foundrygenaiop368102865082 0 Result undefined: /subscriptions/6cb4dbdc-453c-4b5c-9a44-0fb71f3c6d7c/resourceGroups/foundrygenaiops/providers/Microsoft.Search/searchServices/foundrygenaiops368102865082 0 Result undefined: /subscriptions/6cb4dbdc-453c-4b5c-9a44-0fb71f3c6d7c/resourceGroups/investment/providers/Microsoft.CognitiveServices/accounts/admin-mhuye0c2-uksouth 1 Result undefined: /subscriptions/6cb4dbdc-453c-4b5c-9a44-0fb71f3c6d7c/resourceGroups/investment/providers/Microsoft.CognitiveServices/accounts/investinsider 0 Result undefined: /subscriptions/6cb4dbdc-453c-4b5c-9a44-0fb71f3c6d7c/resourceGroups/investment/providers/Microsoft.CognitiveServices/accounts/investmentDI 0 Result undefined: /subscriptions/6cb4dbdc-453c-4b5c-9a44-0fb71f3c6d7c/resourceGroups/nl2sqldax/providers/Microsoft.CognitiveServices/accounts/nl2sqldax 0 Result undefined: /subscriptions/6cb4dbdc-453c-4b5c-9a44-0fb71f3c6d7c/resourceGroups/rg-daxagentfab/providers/Microsoft.CognitiveServices/accounts/ai0-xvee4r5oyiktk 0 Result undefined: /subscriptions/6cb4dbdc-453c-4b5c-9a44-0fb71f3c6d7c/resourceGroups/rg-daxagentfab/providers/Microsoft.CognitiveServices/accounts/oai0-xvee4r5oyiktk 0 Result undefined: /subscriptions/6cb4dbdc-453c-4b5c-9a44-0fb71f3c6d7c/resourceGroups/rg-daxagentfab/providers/Microsoft.Search/searchServices/search0-xvee4r5oyiktk 0 Result undefined: /subscriptions/6cb4dbdc-453c-4b5c-9a44-0fb71f3c6d7c/resourceGroups/rg-ragchatdr1/providers/Microsoft.CognitiveServices/accounts/aisa-okotsq3uvfygg 1 Result undefined: /subscriptions/6cb4dbdc-453c-4b5c-9a44-0fb71f3c6d7c/resourceGroups/rg-ragchatdr2/providers/Microsoft.CognitiveServices/accounts/aisa-rpi42xeqss7is 1 Result undefined: /subscriptions/6cb4dbdc-453c-4b5c-9a44-0fb71f3c6d7c/resourceGroups/rg-ragchatdr2/providers/Microsoft.Search/searchServices/srch-rpi42xeqss7is 0 Result undefined: /subscriptions/6cb4dbdc-453c-4b5c-9a44-0fb71f3c6d7c/resourceGroups/rg-ragchatdr7/providers/Microsoft.CognitiveServices/accounts/aisa-klzfrvxhhxe6s 1 Result undefined: /subscriptions/6cb4dbdc-453c-4b5c-9a44-0fb71f3c6d7c/resourceGroups/rg-ragchatdr7/providers/Microsoft.Search/searchServices/srch-klzfrvxhhxe6s 0 Result undefined: /subscriptions/6cb4dbdc-453c-4b5c-9a44-0fb71f3c6d7c/resourceGroups/rg-ragchatpriv/providers/Microsoft.CognitiveServices/accounts/cog-di-uglzyw3ohprsw 1 Result undefined: /subscriptions/6cb4dbdc-453c-4b5c-9a44-0fb71f3c6d7c/resourceGroups/rg-ragchatpriv/providers/Microsoft.CognitiveServices/accounts/cog-uglzyw3ohprsw 1 Result undefined: /subscriptions/6cb4dbdc-453c-4b5c-9a44-0fb71f3c6d7c/resourceGroups/rg-ragchatpriv/providers/Microsoft.Search/searchServices/gptkb-uglzyw3ohprsw 1 Result undefined: /subscriptions/6cb4dbdc-453c-4b5c-9a44-0fb71f3c6d7c/resourceGroups/rg-retailrag/providers/Microsoft.CognitiveServices/accounts/aoai-6tngxvobrsc3i 0 Result undefined: /subscriptions/6cb4dbdc-453c-4b5c-9a44-0fb71f3c6d7c/resourceGroups/rg-retailrag/providers/Microsoft.Search/searchServices/srch-6tngxvobrsc3i 0 Result undefined: /subscriptions/6cb4dbdc-453c-4b5c-9a44-0fb71f3c6d7c/resourceGroups/rg-translate/providers/Microsoft.CognitiveServices/accounts/agentspanish 0 Result undefined: /subscriptions/6cb4dbdc-453c-4b5c-9a44-0fb71f3c6d7c/resourceGroups/rg-travelagentMAF/providers/Microsoft.CognitiveServices/accounts/travelagentmaf 1 Result undefined: /subscriptions/6cb4dbdc-453c-4b5c-9a44-0fb71f3c6d7c/resourceGroups/rg-travelagentobs/providers/Microsoft.CognitiveServices/accounts/travelagentobs 1 Result undefined: /subscriptions/6cb4dbdc-453c-4b5c-9a44-0fb71f3c6d7c/resourceGroups/rg-travelagent/providers/Microsoft.CognitiveServices/accounts/travelagentdemo 1 | L14: More info | N14: resources | where type =~ 'Microsoft.CognitiveServices/accounts' or type == 'microsoft.search/searchservices' | project id, compliant = (properties.disableLocalAuth == true) | O14: 11cc57b4-a4b1-4410-b439-58a8c2289b3d
A15: AI.103 | B15: Network Topology and Connectivity | C15: Azure OpenAI | D15: Security | E15: Azure OpenAI | F15: Restrict access to select virtual networks or use private endpoints. | H15: High | I15: Fulfilled | L15: More info | O15: c9635b24-65e0-41c9-a442-53f320f2054f
A16: AI.104 | B16: Network Topology and Connectivity | C16: Azure AI Services (Speech, Bing, Translator etc.) | D16: Security | E16: Azure AI Services | F16: Restrict access to select virtual networks or use private endpoints. | H16: High | I16: Fulfilled | L16: More info | O16: bdd4c29c-da1f-4632-b8ac-b48f713981b1
A17: AI.105 | B17: Network Topology and Connectivity | C17: Azure Machine Learning | D17: Security | E17: Azure Machine Learning | F17: Restrict network access to Azure Machine Learning resources. | H17: High | I17: Fulfilled | L17: More info | O17: d0675476-5676-4392-b98e-953c2720554d
A18: AI.106 | B18: Network Topology and Connectivity | C18: Azure AI Services | D18: Security | E18: Azure AI Services | F18: Configure data loss prevention for Azure AI services. | H18: High | I18: Not required | L18: More info | O18: b0ffe298-2f44-4af0-94c6-250e732b3e28
A19: AI.107 | B19: Network Topology and Connectivity | C19: Azure AI Foundry | D19: Security | E19: Azure AI Foundry | F19: Limit outbound traffic from your AI resources. | H19: High | I19: Fulfilled | L19: More info | O19: fa191645-9897-4e46-82a7-d30aa352f7d2
A20: AI.108 | B20: Network Topology and Connectivity | C20: Azure Machine Learning | D20: Security | E20: Azure Machine Learning | F20: Allow only approved network outbound mode. | H20: High | I20: Fulfilled | L20: More info | O20: 3b85ba90-0f99-4b74-ab1f-40ca251f3706
A21: AI.109 | B21: Network Topology and Connectivity | C21: API Gateway | D21: Security | E21: Azure API Management | F21: Deploy a API Gateway solution like API-Management to load balance requests, rate limit tokens, keyless authentication and monitor AI usage. | H21: High | I21: Open | L21: More info | O21: 129b5c68-132e-4839-ac3a-ebe7c14bc08e
A22: AI.11 | B22: BC and DR | C22: Load balancing | D22: Reliability | E22: Azure OpenAI | F22: Deploy separate fine tuned models across regions if finetuning is employed | H22: Medium | I22: Not required | J22: Not required for lab env | L22: More info | O22: 7f154e3a-a369-4282-ae7e-316183687a04
A23: AI.110 | B23: Network Topology and Connectivity | C23: Azure AI Foundry | D23: Security | E23: Azure AI Foundry | F23: Configure the AI managed network and use private endpoints. | H23: High | I23: Fulfilled | L23: More info | O23: e3a78016-e8d8-4598-9cbf-02599ff12e3d
A24: AI.111 | B24: Operations | C24: Operations | D24: Security | E24: Azure Container Apps | F24: Use Dynamic Sessions in Azure Container Apps, to ensure each code execution occurs in a fresh, isolated environment that is destroyed after use. | H24: High | I24: Fulfilled | L24: More info | O24: be2ade6f-bea6-4092-9dab-49e8f8c2ddb7
A25: AI.112 | B25: Operations | C25: Operations | D25: Security | E25: NA | F25: Set resource limits (CPU, memory, disk usage) for code execution environments to prevent any single execution from consuming excessive resources. | H25: Medium | I25: Fulfilled | O25: 2ba176b3-5d95-4caf-a870-0b0ecd65c3af
A26: AI.113 | B26: Operations | C26: Monitoring | D26: Performance | E26: Azure AI Foundry | F26: Implement a monitoring system to ensure that AI workloads remain aligned with KPIs. | H26: High | I26: Fulfilled | L26: More info | O26: 988b2b85-208c-44f9-9b0d-e81327060c25
A27: AI.114 | B27: Operations | C27: Monitoring | D27: Performance | E27: Azure AI Foundry | F27: Proactively identify performance bottlenecks and anomalies. | H27: High | I27: Fulfilled | L27: More info | O27: 48a9f4af-7ab1-45c3-9d62-e06d9df08986
A28: AI.115 | B28: Operations | C28: Monitoring | D28: Operations | E28: Azure Service Health | F28: Include service and resource health events as part of the overall platform monitoring solution. | H28: High | I28: Fulfilled | L28: More info | O28: 6181f3aa-1b06-4ece-b0fe-b373f2ca30d9
A29: AI.116 | B29: Operations | C29: Monitoring | D29: Operations | E29: Azure Monitor | F29: Deploy AMBA to establish monitoring for platform components of your landing zone. | H29: Medium | I29: Not verified | L29: More info | O29: b49dd9e6-e189-4fc5-a02d-d5cc04583d1d
A30: AI.117 | B30: Operations | C30: Operations | D30: Operations | E30: Azure AI Services | F30: Track retirement for pretrained models avoids performance issues when vendor support ends. | H30: High | I30: Open | L30: More info | O30: d71bb244-4ec4-4f61-9ff1-cfdffc0c8036
A31: AI.118 | B31: Operations | C31: Operations | D31: Operations | E31: Azure AI Foundry | F31: Schedule regular retraining based on model performance or business needs to ensure the AI system stays relevant. | H31: High | I31: Open | L31: More info | O31: e0572cb0-cd12-450c-950c-b007c0fc2afb
A32: AI.119 | B32: Operations | C32: Operations | D32: Operations | E32: Azure AI Foundry | F32: Establish model promotion process to promote trained, fine-tuned, and retrained models to higher environments based on performance criteria. | H32: Medium | I32: Open | L32: More info | O32: b73836e9-356c-4aaf-8a2d-af4cd51dfcc1
A33: AI.12 | B33: BC and DR | C33: Data Backup and Disaster Recovery | D33: Reliability | E33: Azure OpenAI | F33: Regularly backup and replicate critical data to ensure data availability and recoverability in case of data loss or system failures. Leverage Azure's backup and disaster recovery services to protect your data. | H33: Medium | I33: Not required | J33: Not required for lab env | L33: More info | O33: 77a1f893-5bda-4433-84f2-4811633182ba
A34: AI.120 | B34: Operations | C34: Operations | D34: Operations | E34: Azure AI Foundry | F34: Standardize compute management for Azure AI Foundry. | H34: Medium | I34: Fulfilled | L34: More info | O34: 79eca34e-0aeb-4160-9fe8-0ff5c647e1c7
A35: AI.121 | B35: Operations | C35: Operations | D35: Operations | E35: Azure Machine Learning | F35: Standardize compute management for Azure Machine Learning. | H35: Medium | I35: Fulfilled | L35: More info | O35: a35efa79-4227-4c84-a038-e19d8b8c365f
A36: AI.122 | B36: Operations | C36: Operations | D36: Operations | E36: Azure Resource Manager | F36: Use resource locks to prevent accidental deletion of critical shared services. | H36: High | I36: Fulfilled | L36: More info | O36: 200a5d55-e0be-450c-83c1-4af6c44fd4bd
A37: AI.123 | B37: Operations | C37: Operations | D37: Security | E37: Azure Open AI | F37: Enforce recommended guardrails for Azure Open AI | H37: Medium | I37: Fulfilled | L37: More info | O37: c4a479ba-3007-4ef8-b845-c15febd3c3e3
A38: AI.124 | B38: Operations | C38: Operations | D38: Security | E38: Azure Machine Learning | F38: Enforce recommended guardrails for Machine Learning. | H38: Medium | I38: Not required | L38: More info | O38: 2355aba7-e21a-4bb0-b89a-99597783f4b2
A39: AI.125 | B39: Operations | C39: Operations | D39: Security | E39: Azure AI Services | F39: Enforce recommended guardrails for Azure AI Services. | H39: Medium | I39: Not required | L39: More info | O39: 12ff613a-8408-4ac5-915f-5f46cf7fd970
A40: AI.126 | B40: Operations | C40: Operations | D40: Security | E40: Azure API Management | F40: Enforce recommended guardrails for API Management | H40: Medium | I40: Not required | L40: More info | O40: 65a0e89a-d016-4eda-b366-af816f1344d6
A41: AI.127 | B41: Operations | C41: Operations | D41: Operations | E41: Azure AI Search | F41: Ensure high-quality data in the correct format, and likely chunked, enriched, and embedded for AI model consumption. | H41: High | I41: Fulfilled | L41: More info | O41: 86617182-f039-4f35-ad77-25419a3c98df
A42: AI.128 | B42: Operations | C42: Operations | D42: Operations | E42: Azure AI Foundry | F42: Manage model versioning and detect drift and set alerts when model predictions or LLM responses start to deviate from expected behavior. | H42: Medium | I42: Fulfilled | L42: More info | O42: 2181bc5a-da1e-4b2e-b83b-4398398f34c2
A43: AI.129 | B43: Operations | C43: Load Balancing | D43: Operations | E43: Azure OpenAI | F43: Consider Gateway patterns with APIM or solutions like AI central for better rate limiting, load balancing, authentication and logging | H43: High | I43: Not required | L43: More info | O43: d4391898-cd28-48be-b6b1-7cb8245451e1
A44: AI.13 | B44: BC and DR | C44: SLA considerations | D44: Reliability | E44: Azure OpenAI | F44: Azure AI search service tiers should be choosen to have a SLA | H44: High | I44: Fulfilled | J44: Result undefined: /subscriptions/6cb4dbdc-453c-4b5c-9a44-0fb71f3c6d7c/resourceGroups/ADWFab/providers/Microsoft.Search/searchServices/aidwfab 0 Result undefined: /subscriptions/6cb4dbdc-453c-4b5c-9a44-0fb71f3c6d7c/resourceGroups/foundrygenaiops/providers/Microsoft.Search/searchServices/foundrygenaiops368102865082 0 Result undefined: /subscriptions/6cb4dbdc-453c-4b5c-9a44-0fb71f3c6d7c/resourceGroups/rg-daxagentfab/providers/Microsoft.Search/searchServices/search0-xvee4r5oyiktk 0 Result undefined: /subscriptions/6cb4dbdc-453c-4b5c-9a44-0fb71f3c6d7c/resourceGroups/rg-ragchatdr2/providers/Microsoft.Search/searchServices/srch-rpi42xeqss7is 0 Result undefined: /subscriptions/6cb4dbdc-453c-4b5c-9a44-0fb71f3c6d7c/resourceGroups/rg-ragchatdr7/providers/Microsoft.Search/searchServices/srch-klzfrvxhhxe6s 0 Result undefined: /subscriptions/6cb4dbdc-453c-4b5c-9a44-0fb71f3c6d7c/resourceGroups/rg-ragchatpriv/providers/Microsoft.Search/searchServices/gptkb-uglzyw3ohprsw 0 Result undefined: /subscriptions/6cb4dbdc-453c-4b5c-9a44-0fb71f3c6d7c/resourceGroups/rg-retailrag/providers/Microsoft.Search/searchServices/srch-6tngxvobrsc3i 0 | L44: More info | N44: resources | where type == 'microsoft.search/searchservices' | extend compliant = (sku.name != 'free' and properties.replicaCount >= 3) | project id, compliant | O44: 95b96ad8-844c-4e3b-8b38-b876ba2cf204
A45: AI.130 | B45: Operations | C45: Monitoring | D45: Operations | E45: Azure OpenAI | F45: Enable monitoring for your AOAI instances | H45: High | I45: Fulfilled | L45: More info | O45: aed3453a-ec72-4392-97a1-52d6cc5e4029
A46: AI.131 | B46: Operations | C46: Alerts | D46: Operations | E46: Azure OpenAI | F46: Create alerts to notify teams of events such as an entry in the activity log created by an action performed on the resource, such as regenerating its subscription keys or a metric threshold such as the number of errors exceeding 10 in an hour | H46: High | I46: Not verified | L46: More info | N46: resources | where type == 'microsoft.insights/metricalerts' | extend compliant = (properties.targetResourceType =~ 'Microsoft.CognitiveServices/accounts') | project id, compliant | O46: 697cb391-ed16-4b2d-886f-0a0241addde6
A47: AI.132 | B47: Operations | C47: Monitoring | D47: Operations | E47: Azure OpenAI | F47: Monitor token usage to prevent service disruptions due to capacity | H47: High | I47: Fulfilled | L47: More info | O47: 8a477cde-b486-41bc-9bc1-0ae66e25d4d5
A48: AI.133 | B48: Operations | C48: Observability | D48: Operations | E48: Azure OpenAI | F48: observe metrics like processed inference tokens, generated completion tokens monitor for rate limit | H48: Medium | I48: Fulfilled | L48: More info | O48: a3aec2c4-e243-46b0-936c-b45e17960eee
A49: AI.134 | B49: Operations | C49: Observability | D49: Operations | E49: Azure OpenAI | F49: Enable and configure Diagnostics for the Azure OpenAI Service. If not sufficient, consider using a gateway such as Azure API Managements in front of Azure OpenAI to log both incoming prompts and outgoing responses, where permitted | H49: Low | I49: Fulfilled | L49: More info | O49: fbdf4cc2-eec4-4d76-8c31-d25ffbb46a39
A50: AI.135 | B50: Operations | C50: Infrastructure Deployment | D50: Operations | E50: Azure OpenAI | F50: Use Infrastructure as code to deploy the Azure OpenAI Service, model deployments, and all related resources | H50: High | I50: Fulfilled | L50: More info | O50: 3af30ed3-2947-498b-8178-a2c5a46ceb54
A51: AI.136 | B51: Operations | C51: Hosting model | D51: Performance | E51: Azure OpenAI | F51: Evaluate usage of Provisioned throughput model | H51: High | I51: Not required | L51: More info | O51: 68889535-e327-4897-b31b-67d67be5962a
A52: AI.137 | B52: Operations | C52: Throughput definition | D52: Performance | E52: Azure OpenAI | F52: Define and evaluate the throughput of the system based on tokens & response per minute and align with requirements | H52: High | I52: Open | L52: More info | O52: 1193846d-697c-4b39-8ed1-6b2d186f0a02
A53: AI.138 | B53: Operations | C53: Latency improvement | D53: Performance | E53: Azure OpenAI | F53: Improve latency of the system by limiting token sizes, streaming options for applications like chatbots or conversational interfaces. Streaming can enhance the perceived performance of Azure OpenAI applications by delivering responses to users in an incremental manner | H53: Medium | I53: Fulfilled | L53: More info | O53: 41addde6-8a47-47cd-bb48-61bc3bc10ae6
A54: AI.139 | B54: Operations | C54: Elasticity segregation | D54: Performance | E54: Azure OpenAI | F54: Estimate elasticity demands to determine synchronous and batch request segregation based on priority. For high priority, use synchronous approach and for low priority, asynchronous batch processing with queue is preferred | H54: Medium | I54: Open | L54: More info | O54: 6e25d4d5-a3ae-4c2c-9e24-36b0336cb45e
A55: AI.14 | B55: Cost Governance | C55: Cost Management | D55: Cost | E55: Azure OpenAI | F55: Verify PTU cost savings vs pay as you pricing for Azure OpenAI and OpenAI models. | H55: High | I55: Not required | J55: Not required for lab env | L55: More info | O55: 4bfd472f-6860-4b27-a90c-a34b36b296cb
A56: AI.140 | B56: Operations | C56: Benchmarking | D56: Performance | E56: Azure OpenAI | F56: Benchmark token consumption requirements based on estimated demands from consumers. Consider using the Azure OpenAI benchmarking tool to help you validate the throughput if you are using Provisioned Throughput Unit deployments | H56: High | I56: Not verified | L56: More info | O56: 5bda4332-4f24-4811-9331-82ba51752694
A57: AI.141 | B57: Operations | C57: Elasticity | D57: Performance | E57: Azure OpenAI | F57: If you are using Provisioned Throughput Units (PTUs), consider deploying a token-per-minute (TPM) deployment for overflow requests. Use a gateway to route requests to the TPM deployment when the PTU limits are reached. | H57: Medium | I57: Not required | L57: More info | O57: 4008ae7d-7e47-4432-96d8-bdcf55bce619
A58: AI.142 | B58: Operations | C58: Model choice | D58: Performance | E58: Azure OpenAI | F58: Choose the right model for the right task. Pick models with right tradeoff between speed, quality of response and output complexity | H58: High | I58: Fulfilled | L58: More info | O58: e8a13f98-8794-424d-9267-86d60b96c97b
A59: AI.143 | B59: Operations | C59: Fine tuning | D59: Performance | E59: Azure OpenAI | F59: Have a baseline for performance without fine-tuning for knowing whether or not fine-tuning has improved model performance | H59: Medium | I59: Fulfilled | L59: More info | O59: e9951904-8384-45c9-a6cb-2912156a1147
A60: AI.144 | B60: Operations | C60: AI Search Vector Limits | D60: Operations | E60: Azure OpenAI | F60: Plan and manage AI Search Vector storage | H60: Medium | I60: Fulfilled | L60: More info | O60: 3266b225-86f4-4a16-92bd-ddea8a487cde
A61: AI.145 | B61: Operations | C61: DevOps | D61: Operations | E61: Azure OpenAI | F61: Ensure deployment of Azure OpenAI instances across your various environments, such as development, test, and production supporting lrarning & experimentation. Apply LLMOps practices to automate the lifecycle management of your GenAI applications | H61: Medium | I61: Fulfilled | L61: More info | O61: b4861bc3-bc14-4aeb-9e66-e8d9a3aec218
A62: AI.146 | B62: Operations | C62: DevOps | D62: Operations | E62: Azure OpenAI | F62: Evaluate the quality of prompts and applications when switching between model versions | H62: Medium | I62: Fulfilled | L62: More info | O62: e6436b07-36db-455f-9796-03334bdf9cc2
A63: AI.147 | B63: Operations | C63: Development | D63: Operations | E63: Azure OpenAI | F63: Evaluate, monitor and refine your GenAI apps for features like groundedness, relevance, accuracy, coherence and fluency | H63: Medium | I63: Fulfilled | L63: More info | O63: 3418db61-2712-4650-9bb4-7a393a080327
A64: AI.148 | B64: Operations | C64: Development | D64: Operations | E64: Azure OpenAI | F64: Evaluate your Azure AI Search results based on different search parameters | H64: Medium | I64: Fulfilled | O64: 294798b1-578b-4219-a46c-eb5443513592
A65: AI.149 | B65: Operations | C65: Development | D65: Operations | E65: Azure OpenAI | F65: Look at fine tuning models as way of increasing accuracy only when you have tried other basic approaches like prompt engineering and RAG with your data | H65: Medium | I65: Not required | L65: More info | O65: 2744293b-b628-4537-a551-19b08e8f5854
A66: AI.15 | B66: Cost Governance | C66: Cost Management | D66: Cost | E66: Azure OpenAI | F66: Ensure the right and cost effective model is in use, unless the use case demands a more expensive model. | H66: Medium | I66: Fulfilled | J66: GPT 4.1 mini | L66: More info | O66: d59e6d68-eaa3-4eec-b2c9-f7bf55bea7f6
A67: AI.150 | B67: Operations | C67: Development | D67: Operations | E67: Azure OpenAI | F67: Use prompt engineering techniques to improve the accuracy of LLM responses | H67: Medium | I67: Fulfilled | L67: More info | O67: 287d9cec-166c-4d07-8af9-b141a898a535
A68: AI.151 | B68: Operations | C68: End user feedback | D68: Operations | E68: Azure OpenAI | F68: Provide end users with scoring options for LLM responses and track these scores. | H68: Medium | I68: Fulfilled | L68: More info | O68: edb117e6-76aa-4f66-aca4-8e5a95f2223e
A69: AI.152 | B69: Operations | C69: Load Balancing | D69: Operations | E69: Azure OpenAI | F69: Use Load balancer solutions like APIM based gateway for balancing load and capacity across services and regions | H69: Medium | I69: Not required | L69: More info | O69: 9de0d5d7-31d4-41e3-911c-817bfafbc410
A70: AI.153 | B70: Operations | C70: Fine tuning | D70: Reliability | E70: Azure OpenAI | F70: Follow the guidance for fine-tuning with large data files and import the data from an Azure blob store. Large files, 100 MB or larger, can become unstable when uploaded through multipart forms because the requests are atomic and can't be retried or resumed | H70: Medium | I70: Not required | L70: More info | O70: 9de0d5d7-31d4-41e3-911c-817bfafbc411
A71: AI.154 | B71: Operations | C71: Monitoring | D71: Reliability | E71: Azure OpenAI | F71: Manage rate limits for your model deployments and monitor usage of tokens per minute (TPM) and requests per minute (RPM) for pay-as-you-go deployments | H71: Medium | I71: Open | L71: More info | O71: 9de0d5d7-31d4-41e3-911c-817bfafbc412
A72: AI.155 | B72: Operations | C72: Monitoring | D72: Reliability | E72: Azure OpenAI | F72: Monitor provision-managed utilization if you're using the provisioned throughput payment model | H72: Medium | I72: Not required | L72: More info | O72: 9de0d5d7-31d4-41e3-911c-817bfafbc413
A73: AI.156 | B73: Operations | C73: IaC | D73: Operations | E73: Azure OpenAI | F73: Use infrastructure as code (IaC) to deploy Azure OpenAI, model deployments, and other infrastructure required for fine-tuning models | H73: Medium | I73: Fulfilled | L73: More info | O73: b4861bc3-bc14-4aeb-9e66-e8d9a3aec219
A74: AI.157 | B74: Operations | C74: Development | D74: Operations | E74: Azure OpenAI | F74: Consider using dedicated model deployments per consumer group to provide per-model usage isolation that can help prevent noisy neighbors between your consumer groups | H74: Medium | I74: Not verified | L74: More info | O74: 2744293b-b628-4537-a551-19b08e8f5855
A75: AI.158 | B75: Operations | C75: High Availablity | D75: Reliability | E75: Cognitive Search | F75: Enable 2 replicas to have 99.9% availability for read operations | H75: High | I75: Not required | L75: More info | O75: 41faa1ed-b7f0-447d-8cba-4a4905e5bb83
A76: AI.159 | B76: Operations | C76: High Availablity | D76: Reliability | E76: Cognitive Search | F76: Enable 3 replicas to have 99.9% availability for read/write operations | H76: Medium | I76: Not required | L76: More info | O76: 7d956fd9-788a-4845-9b9f-c0340972d810
A77: AI.16 | B77: Cost Governance | C77: Cost Management | D77: Cost | E77: Azure OpenAI | F77: Allocate provisioning quotas for each model based on expected workloads to prevent unnecessary costs. | H77: Medium | I77: Fulfilled | J77: 100 TPM for eval models | L77: More info | O77: ec8f4d8c-98b0-4507-9213-3cafc4c2217e
A78: AI.160 | B78: Operations | C78: High Availablity | D78: Reliability | E78: Cognitive Search | F78: Leverage Availability Zones by enabling read and/or write replicas | H78: High | I78: Not required | L78: More info | O78: 44dc5f2b-a032-4d03-aae8-90c3f2c0a4c3
A79: AI.161 | B79: Operations | C79: Georeplication | D79: Reliability | E79: Cognitive Search | F79: For regional redudancy, Manually create services in 2 or more regions for Search as it doesn't provide an automated method of replicating search indexes across geographic regions | H79: Medium | I79: Not required | L79: More info | O79: cd0730f0-0ff1-4b77-9a2b-2a1f7dd5e291
A80: AI.162 | B80: Operations | C80: Georeplication | D80: Reliability | E80: Cognitive Search | F80: To synchronize data across multiple services either Use indexers for updating content on multiple services or Use REST APIs for pushing content updates on multiple services | H80: Medium | I80: Not required | L80: More info | O80: 3c964882-aec9-4d44-9f68-4b5f2efbbdb6
A81: AI.163 | B81: Operations | C81: Georeplication | D81: Reliability | E81: Cognitive Search | F81: Use Azure Traffic Manager to coordinate requests | H81: Medium | I81: Open | L81: More info | O81: 85ee93c9-f53c-4803-be51-e6e4aa37ff4e
A82: AI.164 | B82: Operations | C82: Disaster Recovery | D82: Reliability | E82: Cognitive Search | F82: Backup and Restore an Azure Cognitive Search Index. Use this sample code to back up index definition and snapshot to a series of Json files | H82: High | I82: Open | L82: More info | O82: 7be10278-57c1-4a61-8ee3-895aebfec5aa
A83: AI.165 | B83: Operations | C83: Best Practice | D83: Reliability | E83: Cognitive Services | F83: Leverage FTA HandBook for Cognitive Services | H83: Medium | I83: Not verified | L83: More info | O83: 21c30d25-ffb7-4f6a-b9ea-b3fec328f787
A84: AI.166 | B84: Operations | C84: Backup | D84: Reliability | E84: Cognitive Services | F84: Backup Your Prompts | H84: Medium | I84: Not verified | L84: More info | O84: 78c34698-16b2-4763-aefe-1b9b599de0d5
A85: AI.167 | B85: Operations | C85: Backup | D85: Reliability | E85: Cognitive Services | F85: Business Continuity and Disaster Recovery (BCDR) considerations with Azure OpenAI Service | H85: High | I85: Not required | L85: More info | O85: 750ab2ab-039d-4a6d-95d7-c892adb107d5
A86: AI.168 | B86: Operations | C86: Backup | D86: Reliability | E86: Cognitive Services | F86: Backup Your ChatGPT conversations | H86: Medium | I86: Not required | L86: More info | O86: 325af625-ca44-4e46-a5e2-223ace8bb123
A87: AI.169 | B87: Operations | C87: DevOps | D87: Reliability | E87: Cognitive Services | F87: CI/CD for custom speech | H87: Medium | I87: Not required | L87: More info | O87: 07ca5f17-f154-4e3a-a369-2829e7e31618
A88: AI.17 | B88: Cost Governance | C88: Cost Management | D88: Cost | E88: Azure OpenAI | F88: Use the right deployment type, global deployment offers lower cost-per-token pricing on certain GPT models. | H88: High | I88: Fulfilled | J88: Global Deployment | L88: More info | O88: 3847ab4c-ce03-478f-bd89-caf0ec11b781
A89: AI.170 | B89: Operations | C89: QnA Service | D89: Reliability | E89: Cognitive Services | F89: Move a knowledge base using export-import | H89: Low | I89: Not required | L89: More info | O89: 3687a046-7a1f-4893-9bda-43324f248116
A90: AI.171 | B90: Governance and Security | C90: Metaprompting | D90: Operations | E90: Azure OpenAI | F90: Follow Metaprompting guardrails for resonsible AI | H90: High | I90: Fulfilled | L90: More info | O90: a85b86ad-884f-48e3-9273-4b875ba18f10
A91: AI.172 | B91: Governance and Security | C91: Evaluation | D91: Operations | E91: Azure OpenAI | F91: Evaluate the performance/accuracy of the system with a known golden dataset which has the inputs and the correct answers. Leverage capabilities in PromptFlow for Evaluation. | H91: High | I91: Fulfilled | L91: More info | O91: 4e4f1854-287d-45cd-a126-cc031af5b1fc
A92: AI.173 | B92: Governance and Security | C92: Content Safety | D92: Operations | E92: Azure OpenAI | F92: Review and implement Azure AI content safety | H92: High | I92: Fulfilled | L92: More info | O92: cd288bed-6b17-4cb8-8454-51e1aed3453a
A93: AI.174 | B93: Governance and Security | C93: UX best practice | D93: Operations | E93: Azure OpenAI | F93: Review the considerations in HAI toolkit guidance and apply those interaction practices for the slution | H93: Medium | I93: Open | J93: Future release | L93: More info | O93: ec723923-7a15-42d6-ac5e-402925387e5c
A94: AI.175 | B94: Governance and Security | C94: Jail break Safety | D94: Operations | E94: Azure OpenAI | F94: Implement Prompt shields and groundedness detection using Content Safety | H94: High | I94: Fulfilled | L94: More info | O94: a9c27d9c-42bb-46bd-8c69-99a246f3389a
A95: AI.176 | B95: Governance and Security | C95: Governance | D95: Operations | E95: Azure OpenAI | F95: Adhere to Azure OpenAI or other LLMs terms of use, policies and guidance and allowed use cases | H95: High | I95: Fulfilled | L95: More info | O95: e29711b1-352b-4eee-879b-588defc4972c
A96: AI.177 | B96: Governance and Security | C96: Content Safety | D96: Reliability | E96: Azure OpenAI | F96: Tune content filters to minimize false positives from overly aggressive filters. | H96: Medium | I96: Open | J96: Future release | L96: More info | O96: 9de0d5d7-31d4-41e3-911c-817bfafbc414
A97: AI.18 | B97: Cost Governance | C97: Cost Management | D97: Cost | E97: NA | F97: Choose the right hosting infrastructure, depending on your solution's needs e.g. managed endpoints, AKS or Azure App Service. | H97: Medium | I97: Fulfilled | J97: managed endpoints | O97: dfe64294-9fc5-4b98-a3dc-7cc7b07621c0
A98: AI.19 | B98: Cost Governance | C98: Cost Management | D98: Cost | E98: Azure AI Foundry | F98: Define and enforce a policy to automatically shutdown Azure AI Foundry and Azure Machine Learning compute instances. | H98: Low | I98: Open | J98: Future release | L98: More info | O98: 187edf80-5592-41ca-b65c-c804e56f7394
A99: AI.2 | B99: Application Deployment | C99: DevOps | D99: Operations | E99: Azure DevOps | F99: Use a CI/CD pipeline to deploy IaC artifacts and ensure the quality of your deployment and Azure environments. | H99: Medium | I99: Fulfilled | J99: azd pipeline config is setup | L99: More info | O99: 9af60e0a-1111-4885-82e2-f9575581673f
A100: AI.20 | B100: Cost Governance | C100: Cost Management | D100: Cost | E100: Azure Cost Management | F100: Configure 'Actual' and 'Forecasted' Budget Alerts. | H100: Medium | I100: Open | J100: Future release | L100: More info | O100: 15912c2a-babb-4b9f-9dc3-73c1489472dd
...

Sheet Dashboard
D1: Reviewed Items | E1: Open Items
A2: Review Status | D2: =IF($T$29=0,0,1-$Q$29/$T$29) -> 0.88636364 | E2: =IF(T29=0,0,R29/T29) -> 0.15909091
B5: =Values!$B$2 -> Not verified | C5: =Values!$B$3 -> Open | D5: =Values!$B$4 -> Fulfilled | E5: =Values!$B$5 -> Not required | F5: =Values!$B$6 -> N/A | J5: =Values!$B$2 -> Not verified | K5: =Values!$B$3 -> Open | L5: =Values!$B$4 -> Fulfilled | M5: =Values!$B$5 -> Not required | N5: =Values!$B$6 -> N/A | O5: Total
A6: =Values!A2 -> High | B6: {=SUMPRODUCT(--(Checklist!$H$10:$L$487=$A6)*--(Checklist!$I$10:$I$487=B$5))} -> 9 | C6: {=SUMPRODUCT(--(Checklist!$H$10:$L$487=$A6)*--(Checklist!$I$10:$I$487=C$5))} -> 12 | D6: {=SUMPRODUCT(--(Checklist!$H$10:$L$487=$A6)*--(Checklist!$I$10:$I$487=D$5))} -> 48 | E6: {=SUMPRODUCT(--(Checklist!$H$10:$L$487=$A6)*--(Checklist!$I$10:$I$487=E$5))} -> 14 | F6: {=SUMPRODUCT(--(Checklist!$H$10:$L$487=$A6)*--(Checklist!$I$10:$I$487=F$5))} -> 0 | G6: =SUM(B6:F6) -> 83 | I6: =IF(Values!$C2="","",Values!$C2) -> Identity and Access Management | J6: {=IF($I6="","",SUMPRODUCT(--(Checklist!$B$10:$B$487=$I6)*--(Checklist!$I$10:$I$487=J$5)))} -> 0 | K6: {=IF($I6="","",SUMPRODUCT(--(Checklist!$B$10:$B$487=$I6)*--(Checklist!$I$10:$I$487=K$5)))} -> 0 | L6: {=IF($I6="","",SUMPRODUCT(--(Checklist!$B$10:$B$487=$I6)*--(Checklist!$I$10:$I$487=L$5)))} -> 6 | M6: {=IF($I6="","",SUMPRODUCT(--(Checklist!$B$10:$B$487=$I6)*--(Checklist!$I$10:$I$487=M$5)))} -> 2 | N6: {=IF($I6="","",SUMPRODUCT(--(Checklist!$B$10:$B$487=$I6)*--(Checklist!$I$10:$I$487=N$5)))} -> 0 | O6: =IF($I6="","",SUM(J6:N6)) -> 8
A7: =Values!A3 -> Medium | B7: {=SUMPRODUCT(--(Checklist!$H$10:$L$487=$A7)*--(Checklist!$I$10:$I$487=B$5))} -> 11 | C7: {=SUMPRODUCT(--(Checklist!$H$10:$L$487=$A7)*--(Checklist!$I$10:$I$487=C$5))} -> 13 | D7: {=SUMPRODUCT(--(Checklist!$H$10:$L$487=$A7)*--(Checklist!$I$10:$I$487=D$5))} -> 37 | E7: {=SUMPRODUCT(--(Checklist!$H$10:$L$487=$A7)*--(Checklist!$I$10:$I$487=E$5))} -> 22 | F7: {=SUMPRODUCT(--(Checklist!$H$10:$L$487=$A7)*--(Checklist!$I$10:$I$487=F$5))} -> 0 | G7: =SUM(B7:F7) -> 83 | I7: =IF(Values!$C3="","",Values!$C3) -> Network Topology and Connectivity | J7: {=IF($I7="","",SUMPRODUCT(--(Checklist!$B$10:$B$487=$I7)*--(Checklist!$I$10:$I$487=J$5)))} -> 0 | K7: {=IF($I7="","",SUMPRODUCT(--(Checklist!$B$10:$B$487=$I7)*--(Checklist!$I$10:$I$487=K$5)))} -> 1 | L7: {=IF($I7="","",SUMPRODUCT(--(Checklist!$B$10:$B$487=$I7)*--(Checklist!$I$10:$I$487=L$5)))} -> 5 | M7: {=IF($I7="","",SUMPRODUCT(--(Checklist!$B$10:$B$487=$I7)*--(Checklist!$I$10:$I$487=M$5)))} -> 1 | N7: {=IF($I7="","",SUMPRODUCT(--(Checklist!$B$10:$B$487=$I7)*--(Checklist!$I$10:$I$487=N$5)))} -> 0 | O7: =IF($I7="","",SUM(J7:N7)) -> 7
A8: =Values!A4 -> Low | B8: {=SUMPRODUCT(--(Checklist!$H$10:$L$487=$A8)*--(Checklist!$I$10:$I$487=B$5))} -> 0 | C8: {=SUMPRODUCT(--(Checklist!$H$10:$L$487=$A8)*--(Checklist!$I$10:$I$487=C$5))} -> 3 | D8: {=SUMPRODUCT(--(Checklist!$H$10:$L$487=$A8)*--(Checklist!$I$10:$I$487=D$5))} -> 6 | E8: {=SUMPRODUCT(--(Checklist!$H$10:$L$487=$A8)*--(Checklist!$I$10:$I$487=E$5))} -> 2 | F8: {=SUMPRODUCT(--(Checklist!$H$10:$L$487=$A8)*--(Checklist!$I$10:$I$487=F$5))} -> 0 | G8: =SUM(B8:F8) -> 11 | I8: =IF(Values!$C4="","",Values!$C4) -> BC and DR | J8: {=IF($I8="","",SUMPRODUCT(--(Checklist!$B$10:$B$487=$I8)*--(Checklist!$I$10:$I$487=J$5)))} -> 0 | K8: {=IF($I8="","",SUMPRODUCT(--(Checklist!$B$10:$B$487=$I8)*--(Checklist!$I$10:$I$487=K$5)))} -> 0 | L8: {=IF($I8="","",SUMPRODUCT(--(Checklist!$B$10:$B$487=$I8)*--(Checklist!$I$10:$I$487=L$5)))} -> 2 | M8: {=IF($I8="","",SUMPRODUCT(--(Checklist!$B$10:$B$487=$I8)*--(Checklist!$I$10:$I$487=M$5)))} -> 7 | N8: {=IF($I8="","",SUMPRODUCT(--(Checklist!$B$10:$B$487=$I8)*--(Checklist!$I$10:$I$487=N$5)))} -> 0 | O8: =IF($I8="","",SUM(J8:N8)) -> 9
B9: =SUM(B6:B8) -> 20 | C9: =SUM(C6:C8) -> 28 | D9: =SUM(D6:D8) -> 91 | E9: =SUM(E6:E8) -> 38 | F9: =SUM(F6:F8) -> 0 | G9: =SUM(G6:G8) -> 177 | I9: =IF(Values!$C5="","",Values!$C5) -> Governance and Security | J9: {=IF($I9="","",SUMPRODUCT(--(Checklist!$B$10:$B$487=$I9)*--(Checklist!$I$10:$I$487=J$5)))} -> 9 | K9: {=IF($I9="","",SUMPRODUCT(--(Checklist!$B$10:$B$487=$I9)*--(Checklist!$I$10:$I$487=K$5)))} -> 17 | L9: {=IF($I9="","",SUMPRODUCT(--(Checklist!$B$10:$B$487=$I9)*--(Checklist!$I$10:$I$487=L$5)))} -> 36 | M9: {=IF($I9="","",SUMPRODUCT(--(Checklist!$B$10:$B$487=$I9)*--(Checklist!$I$10:$I$487=M$5)))} -> 6 | N9: {=IF($I9="","",SUMPRODUCT(--(Checklist!$B$10:$B$487=$I9)*--(Checklist!$I$10:$I$487=N$5)))} -> 0 | O9: =IF($I9="","",SUM(J9:N9)) -> 68
I10: =IF(Values!$C6="","",Values!$C6) -> Cost Governance | J10: {=IF($I10="","",SUMPRODUCT(--(Checklist!$B$10:$B$487=$I10)*--(Checklist!$I$10:$I$487=J$5)))} -> 5 | K10: {=IF($I10="","",SUMPRODUCT(--(Checklist!$B$10:$B$487=$I10)*--(Checklist!$I$10:$I$487=K$5)))} -> 2 | L10: {=IF($I10="","",SUMPRODUCT(--(Checklist!$B$10:$B$487=$I10)*--(Checklist!$I$10:$I$487=L$5)))} -> 10 | M10: {=IF($I10="","",SUMPRODUCT(--(Checklist!$B$10:$B$487=$I10)*--(Checklist!$I$10:$I$487=M$5)))} -> 3 | N10: {=IF($I10="","",SUMPRODUCT(--(Checklist!$B$10:$B$487=$I10)*--(Checklist!$I$10:$I$487=N$5)))} -> 0 | O10: =IF($I10="","",SUM(J10:N10)) -> 20
I11: =IF(Values!$C7="","",Values!$C7) -> Operations | J11: {=IF($I11="","",SUMPRODUCT(--(Checklist!$B$10:$B$487=$I11)*--(Checklist!$I$10:$I$487=J$5)))} -> 6 | K11: {=IF($I11="","",SUMPRODUCT(--(Checklist!$B$10:$B$487=$I11)*--(Checklist!$I$10:$I$487=K$5)))} -> 8 | L11: {=IF($I11="","",SUMPRODUCT(--(Checklist!$B$10:$B$487=$I11)*--(Checklist!$I$10:$I$487=L$5)))} -> 27 | M11: {=IF($I11="","",SUMPRODUCT(--(Checklist!$B$10:$B$487=$I11)*--(Checklist!$I$10:$I$487=M$5)))} -> 19 | N11: {=IF($I11="","",SUMPRODUCT(--(Checklist!$B$10:$B$487=$I11)*--(Checklist!$I$10:$I$487=N$5)))} -> 0 | O11: =IF($I11="","",SUM(J11:N11)) -> 60
I12: =IF(Values!$C8="","",Values!$C8) -> Application Deployment | J12: {=IF($I12="","",SUMPRODUCT(--(Checklist!$B$10:$B$487=$I12)*--(Checklist!$I$10:$I$487=J$5)))} -> 0 | K12: {=IF($I12="","",SUMPRODUCT(--(Checklist!$B$10:$B$487=$I12)*--(Checklist!$I$10:$I$487=K$5)))} -> 0 | L12: {=IF($I12="","",SUMPRODUCT(--(Checklist!$B$10:$B$487=$I12)*--(Checklist!$I$10:$I$487=L$5)))} -> 4 | M12: {=IF($I12="","",SUMPRODUCT(--(Checklist!$B$10:$B$487=$I12)*--(Checklist!$I$10:$I$487=M$5)))} -> 0 | N12: {=IF($I12="","",SUMPRODUCT(--(Checklist!$B$10:$B$487=$I12)*--(Checklist!$I$10:$I$487=N$5)))} -> 0 | O12: =IF($I12="","",SUM(J12:N12)) -> 4
I13: =IF(Values!$C9="","",Values!$C9) | J13: {=IF($I13="","",SUMPRODUCT(--(Checklist!$B$10:$B$487=$I13)*--(Checklist!$I$10:$I$487=J$5)))} | K13: {=IF($I13="","",SUMPRODUCT(--(Checklist!$B$10:$B$487=$I13)*--(Checklist!$I$10:$I$487=K$5)))} | L13: {=IF($I13="","",SUMPRODUCT(--(Checklist!$B$10:$B$487=$I13)*--(Checklist!$I$10:$I$487=L$5)))} | M13: {=IF($I13="","",SUMPRODUCT(--(Checklist!$B$10:$B$487=$I13)*--(Checklist!$I$10:$I$487=M$5)))} | N13: {=IF($I13="","",SUMPRODUCT(--(Checklist!$B$10:$B$487=$I13)*--(Checklist!$I$10:$I$487=N$5)))} | O13: =IF($I13="","",SUM(J13:N13))
J14: =SUM(J6:J13) -> 20 | K14: =SUM(K6:K13) -> 28 | L14: =SUM(L6:L13) -> 90 | M14: =SUM(M6:M13) -> 38 | N14: =SUM(N6:N13) -> 0 | O14: =SUM(O6:O13) -> 176
P20: Category | Q20: =Values!$B$2 -> Not verified | R20: =Values!$B$3 -> Open | S20: Closed | T20: Total | U20: Progress
P21: =IF(Values!$C2="","",Values!$C2) -> Identity and Access Management | Q21: {=IF($P21="","",SUMPRODUCT(--(Checklist!$B$10:$B$487=$P21)*--(Checklist!$I$10:$I$487=Q$20)))} -> 0 | R21: {=IF($P21="","",SUMPRODUCT(--(Checklist!$B$10:$B$487=$P21)*--(Checklist!$I$10:$I$487=R$20)))} -> 0 | S21: {=IF($P21="","",SUMPRODUCT(--(Checklist!$B$10:$B$487=$P21)*(--(Checklist!$I$10:$I$487=Values!$B$4)+--(Checklist!$I$10:$I$487=Values!$B$5)+--(Checklist!$I$10:$I$487=Values!$B$6))))} -> 8 | T21: =IF($P21="","",SUM(Q21:S21)) -> 8 | U21: =IF($P21="","",IF(T21=0,0,S21/T21)) -> 1
P22: =IF(Values!$C3="","",Values!$C3) -> Network Topology and Connectivity | Q22: {=IF($P22="","",SUMPRODUCT(--(Checklist!$B$10:$B$487=$P22)*--(Checklist!$I$10:$I$487=Q$20)))} -> 0 | R22: {=IF($P22="","",SUMPRODUCT(--(Checklist!$B$10:$B$487=$P22)*--(Checklist!$I$10:$I$487=R$20)))} -> 1 | S22: {=IF($P22="","",SUMPRODUCT(--(Checklist!$B$10:$B$487=$P22)*(--(Checklist!$I$10:$I$487=Values!$B$4)+--(Checklist!$I$10:$I$487=Values!$B$5)+--(Checklist!$I$10:$I$487=Values!$B$6))))} -> 6 | T22: =IF($P22="","",SUM(Q22:S22)) -> 7 | U22: =IF($P22="","",IF(T22=0,0,S22/T22)) -> 0.85714286
P23: =IF(Values!$C4="","",Values!$C4) -> BC and DR | Q23: {=IF($P23="","",SUMPRODUCT(--(Checklist!$B$10:$B$487=$P23)*--(Checklist!$I$10:$I$487=Q$20)))} -> 0 | R23: {=IF($P23="","",SUMPRODUCT(--(Checklist!$B$10:$B$487=$P23)*--(Checklist!$I$10:$I$487=R$20)))} -> 0 | S23: {=IF($P23="","",SUMPRODUCT(--(Checklist!$B$10:$B$487=$P23)*(--(Checklist!$I$10:$I$487=Values!$B$4)+--(Checklist!$I$10:$I$487=Values!$B$5)+--(Checklist!$I$10:$I$487=Values!$B$6))))} -> 9 | T23: =IF($P23="","",SUM(Q23:S23)) -> 9 | U23: =IF($P23="","",IF(T23=0,0,S23/T23)) -> 1
P24: =IF(Values!$C5="","",Values!$C5) -> Governance and Security | Q24: {=IF($P24="","",SUMPRODUCT(--(Checklist!$B$10:$B$487=$P24)*--(Checklist!$I$10:$I$487=Q$20)))} -> 9 | R24: {=IF($P24="","",SUMPRODUCT(--(Checklist!$B$10:$B$487=$P24)*--(Checklist!$I$10:$I$487=R$20)))} -> 17 | S24: {=IF($P24="","",SUMPRODUCT(--(Checklist!$B$10:$B$487=$P24)*(--(Checklist!$I$10:$I$487=Values!$B$4)+--(Checklist!$I$10:$I$487=Values!$B$5)+--(Checklist!$I$10:$I$487=Values!$B$6))))} -> 42 | T24: =IF($P24="","",SUM(Q24:S24)) -> 68 | U24: =IF($P24="","",IF(T24=0,0,S24/T24)) -> 0.61764706
P25: =IF(Values!$C6="","",Values!$C6) -> Cost Governance | Q25: {=IF($P25="","",SUMPRODUCT(--(Checklist!$B$10:$B$487=$P25)*--(Checklist!$I$10:$I$487=Q$20)))} -> 5 | R25: {=IF($P25="","",SUMPRODUCT(--(Checklist!$B$10:$B$487=$P25)*--(Checklist!$I$10:$I$487=R$20)))} -> 2 | S25: {=IF($P25="","",SUMPRODUCT(--(Checklist!$B$10:$B$487=$P25)*(--(Checklist!$I$10:$I$487=Values!$B$4)+--(Checklist!$I$10:$I$487=Values!$B$5)+--(Checklist!$I$10:$I$487=Values!$B$6))))} -> 13 | T25: =IF($P25="","",SUM(Q25:S25)) -> 20 | U25: =IF($P25="","",IF(T25=0,0,S25/T25)) -> 0.65
P26: =IF(Values!$C7="","",Values!$C7) -> Operations | Q26: {=IF($P26="","",SUMPRODUCT(--(Checklist!$B$10:$B$487=$P26)*--(Checklist!$I$10:$I$487=Q$20)))} -> 6 | R26: {=IF($P26="","",SUMPRODUCT(--(Checklist!$B$10:$B$487=$P26)*--(Checklist!$I$10:$I$487=R$20)))} -> 8 | S26: {=IF($P26="","",SUMPRODUCT(--(Checklist!$B$10:$B$487=$P26)*(--(Checklist!$I$10:$I$487=Values!$B$4)+--(Checklist!$I$10:$I$487=Values!$B$5)+--(Checklist!$I$10:$I$487=Values!$B$6))))} -> 46 | T26: =IF($P26="","",SUM(Q26:S26)) -> 60 | U26: =IF($P26="","",IF(T26=0,0,S26/T26)) -> 0.76666667
P27: =IF(Values!$C8="","",Values!$C8) -> Application Deployment | Q27: {=IF($P27="","",SUMPRODUCT(--(Checklist!$B$10:$B$487=$P27)*--(Checklist!$I$10:$I$487=Q$20)))} -> 0 | R27: {=IF($P27="","",SUMPRODUCT(--(Checklist!$B$10:$B$487=$P27)*--(Checklist!$I$10:$I$487=R$20)))} -> 0 | S27: {=IF($P27="","",SUMPRODUCT(--(Checklist!$B$10:$B$487=$P27)*(--(Checklist!$I$10:$I$487=Values!$B$4)+--(Checklist!$I$10:$I$487=Values!$B$5)+--(Checklist!$I$10:$I$487=Values!$B$6))))} -> 4 | T27: =IF($P27="","",SUM(Q27:S27)) -> 4 | U27: =IF($P27="","",IF(T27=0,0,S27/T27)) -> 1
P28: =IF(Values!$C9="","",Values!$C9) | Q28: {=IF($P28="","",SUMPRODUCT(--(Checklist!$B$10:$B$487=$P28)*--(Checklist!$I$10:$I$487=Q$20)))} | R28: {=IF($P28="","",SUMPRODUCT(--(Checklist!$B$10:$B$487=$P28)*--(Checklist!$I$10:$I$487=R$20)))} | S28: {=IF($P28="","",SUMPRODUCT(--(Checklist!$B$10:$B$487=$P28)*(--(Checklist!$I$10:$I$487=Values!$B$4)+--(Checklist!$I$10:$I$487=Values!$B$5)+--(Checklist!$I$10:$I$487=Values!$B$6))))} | T28: =IF($P28="","",SUM(Q28:S28)) | U28: =IF($P28="","",IF(T28=0,0,S28/T28))
Q29: =SUM(Q21:Q28) -> 20 | R29: =SUM(R21:R28) -> 28 | S29: =SUM(S21:S28) -> 128 | T29: =SUM(T21:T28) -> 176 | U29: =IF(T29=0,0,S29/T29) -> 0.72727273
A49: Max score only Fulfilled/NotRequired/Open (the rest of the items are ignored)
B50: Min (F/NR/O) | C50: Max (F/NR/O) | D50: F+O | E50: Score | H50: Services | I50: =Values!$L$2 -> Reliability | J50: =Values!$L$3 -> Security | K50: =Values!$L$4 -> Cost | L50: =Values!$L$5 -> Operations | M50: =Values!$L$6 -> Performance | N50: Total
A51: Secure | B51: {=SUMPRODUCT(--(Checklist!$I$10:$I$299=Values!$B$4),Checklist!$P$10:$P$299,--(Checklist!$P$10:$P$299<0))+SUMPRODUCT(--(Checklist!$I$10:$I$299=Values!$B$6),Checklist!$P$10:$P$299,--(Checklist!$P$10:$P$299<0))+SUMPRODUCT(--(Checklist!$I$10:$I$299=Values!$B$3),Checklist!$P$10:$P$299,--(Checklist!$P$10:$P$299<0))} -> 0 | C51: {=SUMPRODUCT(--(Checklist!$I$10:$I$299=Values!$B$4),Checklist!$P$10:$P$299,--(Checklist!$P$10:$P$299>0))+SUMPRODUCT(--(Checklist!$I$10:$I$299=Values!$B$6),Checklist!$P$10:$P$299,--(Checklist!$P$10:$P$299>0))+SUMPRODUCT(--(Checklist!$I$10:$I$299=Values!$B$3),Checklist!$P$10:$P$299,--(Checklist!$P$10:$P$299>0))} -> 0 | D51: {=SUMPRODUCT(--(Checklist!$I$10:$I$299=Values!$B$4),Checklist!$P$10:$P$299)+SUMPRODUCT(--(Checklist!$I$10:$I$299=Values!$B$3),Checklist!$P$10:$P$299)} -> 0 | E51: =IF((C51-B51)=0,1,(D51-B51)/(C51-B51)) -> 1 | H51: {=_xlfn._xlws.SORT(_xlfn.UNIQUE(_xlfn._xlws.FILTER(Checklist!$E$10:$E$2513, Checklist!$E$10:$E$2513<>"")))} -> Azure AI Content Safety | I51: {=IF($H51="","",SUMPRODUCT(--(Checklist!$E$10:$E$2513=$H51)*--(Checklist!$D$10:$D$2513=I$50)))} -> 0 | J51: {=IF($H51="","",SUMPRODUCT(--(Checklist!$E$10:$E$2513=$H51)*--(Checklist!$D$10:$D$2513=J$50)))} -> 3 | K51: {=IF($H51="","",SUMPRODUCT(--(Checklist!$E$10:$E$2513=$H51)*--(Checklist!$D$10:$D$2513=K$50)))} -> 0 | L51: {=IF($H51="","",SUMPRODUCT(--(Checklist!$E$10:$E$2513=$H51)*--(Checklist!$D$10:$D$2513=L$50)))} -> 0 | M51: {=IF($H51="","",SUMPRODUCT(--(Checklist!$E$10:$E$2513=$H51)*--(Checklist!$D$10:$D$2513=M$50)))} -> 0 | N51: =IF($H51="","",SUM(I51:M51)) -> 3
A52: Cost-efficient | B52: {=SUMPRODUCT(--(Checklist!$I$10:$I$299=Values!$B$4),Checklist!$Q$10:$Q$299,--(Checklist!$Q$10:$Q$299<0))+SUMPRODUCT(--(Checklist!$I$10:$I$299=Values!$B$6),Checklist!$Q$10:$Q$299,--(Checklist!$Q$10:$Q$299<0))+SUMPRODUCT(--(Checklist!$I$10:$I$299=Values!$B$3),Checklist!$Q$10:$Q$299,--(Checklist!$Q$10:$Q$299<0))} -> 0 | C52: {=SUMPRODUCT(--(Checklist!$I$10:$I$299=Values!$B$4),Checklist!$Q$10:$Q$299,--(Checklist!$Q$10:$Q$299>0))+SUMPRODUCT(--(Checklist!$I$10:$I$299=Values!$B$6),Checklist!$Q$10:$Q$299,--(Checklist!$Q$10:$Q$299>0))+SUMPRODUCT(--(Checklist!$I$10:$I$299=Values!$B$3),Checklist!$Q$10:$Q$299,--(Checklist!$Q$10:$Q$299>0))} -> 0 | D52: {=SUMPRODUCT(--(Checklist!$I$10:$I$299=Values!$B$4),Checklist!$Q$10:$Q$299)+SUMPRODUCT(--(Checklist!$I$10:$I$299=Values!$B$3),Checklist!$Q$10:$Q$299)} -> 0 | E52: =IF((C52-B52)=0,1,(D52-B52)/(C52-B52)) -> 1 | H52: Azure AI Foundry | I52: {=IF($H52="","",SUMPRODUCT(--(Checklist!$E$10:$E$2513=$H52)*--(Checklist!$D$10:$D$2513=I$50)))} -> 1 | J52: {=IF($H52="","",SUMPRODUCT(--(Checklist!$E$10:$E$2513=$H52)*--(Checklist!$D$10:$D$2513=J$50)))} -> 4 | K52: {=IF($H52="","",SUMPRODUCT(--(Checklist!$E$10:$E$2513=$H52)*--(Checklist!$D$10:$D$2513=K$50)))} -> 1 | L52: {=IF($H52="","",SUMPRODUCT(--(Checklist!$E$10:$E$2513=$H52)*--(Checklist!$D$10:$D$2513=L$50)))} -> 4 | M52: {=IF($H52="","",SUMPRODUCT(--(Checklist!$E$10:$E$2513=$H52)*--(Checklist!$D$10:$D$2513=M$50)))} -> 3 | N52: =IF($H52="","",SUM(I52:M52)) -> 13
A53: Scalable | B53: {=SUMPRODUCT(--(Checklist!$I$10:$I$299=Values!$B$4),Checklist!$R$10:$R$299,--(Checklist!$R$10:$R$299<0))+SUMPRODUCT(--(Checklist!$I$10:$I$299=Values!$B$6),Checklist!$R$10:$R$299,--(Checklist!$R$10:$R$299<0))+SUMPRODUCT(--(Checklist!$I$10:$I$299=Values!$B$3),Checklist!$R$10:$R$299,--(Checklist!$R$10:$R$299<0))} -> 0 | C53: {=SUMPRODUCT(--(Checklist!$I$10:$I$299=Values!$B$4),Checklist!$R$10:$R$299,--(Checklist!$R$10:$R$299>0))+SUMPRODUCT(--(Checklist!$I$10:$I$299=Values!$B$6),Checklist!$R$10:$R$299,--(Checklist!$R$10:$R$299>0))+SUMPRODUCT(--(Checklist!$I$10:$I$299=Values!$B$3),Checklist!$R$10:$R$299,--(Checklist!$R$10:$R$299>0))} -> 0 | D53: {=SUMPRODUCT(--(Checklist!$I$10:$I$299=Values!$B$4),Checklist!$R$10:$R$299)+SUMPRODUCT(--(Checklist!$I$10:$I$299=Values!$B$3),Checklist!$R$10:$R$299)} -> 0 | E53: =IF((C53-B53)=0,1,(D53-B53)/(C53-B53)) -> 1 | H53: Azure AI Search | I53: {=IF($H53="","",SUMPRODUCT(--(Checklist!$E$10:$E$2513=$H53)*--(Checklist!$D$10:$D$2513=I$50)))} -> 0 | J53: {=IF($H53="","",SUMPRODUCT(--(Checklist!$E$10:$E$2513=$H53)*--(Checklist!$D$10:$D$2513=J$50)))} -> 0 | K53: {=IF($H53="","",SUMPRODUCT(--(Checklist!$E$10:$E$2513=$H53)*--(Checklist!$D$10:$D$2513=K$50)))} -> 0 | L53: {=IF($H53="","",SUMPRODUCT(--(Checklist!$E$10:$E$2513=$H53)*--(Checklist!$D$10:$D$2513=L$50)))} -> 2 | M53: {=IF($H53="","",SUMPRODUCT(--(Checklist!$E$10:$E$2513=$H53)*--(Checklist!$D$10:$D$2513=M$50)))} -> 0 | N53: =IF($H53="","",SUM(I53:M53)) -> 2
A54: Simple | B54: {=SUMPRODUCT(--(Checklist!$I$10:$I$299=Values!$B$4),Checklist!$S$10:$S$299,--(Checklist!$S$10:$S$299<0))+SUMPRODUCT(--(Checklist!$I$10:$I$299=Values!$B$6),Checklist!$S$10:$S$299,--(Checklist!$S$10:$S$299<0))+SUMPRODUCT(--(Checklist!$I$10:$I$299=Values!$B$3),Checklist!$S$10:$S$299,--(Checklist!$S$10:$S$299<0))} -> 0 | C54: {=SUMPRODUCT(--(Checklist!$I$10:$I$299=Values!$B$4),Checklist!$S$10:$S$299,--(Checklist!$S$10:$S$299>0))+SUMPRODUCT(--(Checklist!$I$10:$I$299=Values!$B$6),Checklist!$S$10:$S$299,--(Checklist!$S$10:$S$299>0))+SUMPRODUCT(--(Checklist!$I$10:$I$299=Values!$B$3),Checklist!$S$10:$S$299,--(Checklist!$S$10:$S$299>0))} -> 0 | D54: {=SUMPRODUCT(--(Checklist!$I$10:$I$299=Values!$B$4),Checklist!$S$10:$S$299)+SUMPRODUCT(--(Checklist!$I$10:$I$299=Values!$B$3),Checklist!$S$10:$S$299)} -> 0 | E54: =IF((C54-B54)=0,1,(D54-B54)/(C54-B54)) -> 1 | H54: Azure AI Services | I54: {=IF($H54="","",SUMPRODUCT(--(Checklist!$E$10:$E$2513=$H54)*--(Checklist!$D$10:$D$2513=I$50)))} -> 0 | J54: {=IF($H54="","",SUMPRODUCT(--(Checklist!$E$10:$E$2513=$H54)*--(Checklist!$D$10:$D$2513=J$50)))} -> 5 | K54: {=IF($H54="","",SUMPRODUCT(--(Checklist!$E$10:$E$2513=$H54)*--(Checklist!$D$10:$D$2513=K$50)))} -> 0 | L54: {=IF($H54="","",SUMPRODUCT(--(Checklist!$E$10:$E$2513=$H54)*--(Checklist!$D$10:$D$2513=L$50)))} -> 1 | M54: {=IF($H54="","",SUMPRODUCT(--(Checklist!$E$10:$E$2513=$H54)*--(Checklist!$D$10:$D$2513=M$50)))} -> 0 | N54: =IF($H54="","",SUM(I54:M54)) -> 6
A55: Highly available | B55: {=SUMPRODUCT(--(Checklist!$I$10:$I$299=Values!$B$4),Checklist!$T$10:$T$299,--(Checklist!$T$10:$T$299<0))+SUMPRODUCT(--(Checklist!$I$10:$I$299=Values!$B$6),Checklist!$T$10:$T$299,--(Checklist!$T$10:$T$299<0))+SUMPRODUCT(--(Checklist!$I$10:$I$299=Values!$B$3),Checklist!$T$10:$T$299,--(Checklist!$T$10:$T$299<0))} -> 0 | C55: {=SUMPRODUCT(--(Checklist!$I$10:$I$299=Values!$B$4),Checklist!$T$10:$T$299,--(Checklist!$T$10:$T$299>0))+SUMPRODUCT(--(Checklist!$I$10:$I$299=Values!$B$6),Checklist!$T$10:$T$299,--(Checklist!$T$10:$T$299>0))+SUMPRODUCT(--(Checklist!$I$10:$I$299=Values!$B$3),Checklist!$T$10:$T$299,--(Checklist!$T$10:$T$299>0))} -> 0 | D55: {=SUMPRODUCT(--(Checklist!$I$10:$I$299=Values!$B$4),Checklist!$T$10:$T$299)+SUMPRODUCT(--(Checklist!$I$10:$I$299=Values!$B$3),Checklist!$T$10:$T$299)} -> 0 | E55: =IF((C55-B55)=0,1,(D55-B55)/(C55-B55)) -> 1 | H55: Azure API Management | I55: {=IF($H55="","",SUMPRODUCT(--(Checklist!$E$10:$E$2513=$H55)*--(Checklist!$D$10:$D$2513=I$50)))} -> 0 | J55: {=IF($H55="","",SUMPRODUCT(--(Checklist!$E$10:$E$2513=$H55)*--(Checklist!$D$10:$D$2513=J$50)))} -> 3 | K55: {=IF($H55="","",SUMPRODUCT(--(Checklist!$E$10:$E$2513=$H55)*--(Checklist!$D$10:$D$2513=K$50)))} -> 0 | L55: {=IF($H55="","",SUMPRODUCT(--(Checklist!$E$10:$E$2513=$H55)*--(Checklist!$D$10:$D$2513=L$50)))} -> 0 | M55: {=IF($H55="","",SUMPRODUCT(--(Checklist!$E$10:$E$2513=$H55)*--(Checklist!$D$10:$D$2513=M$50)))} -> 0 | N55: =IF($H55="","",SUM(I55:M55)) -> 3
H56: Azure Container Apps | I56: {=IF($H56="","",SUMPRODUCT(--(Checklist!$E$10:$E$2513=$H56)*--(Checklist!$D$10:$D$2513=I$50)))} -> 0 | J56: {=IF($H56="","",SUMPRODUCT(--(Checklist!$E$10:$E$2513=$H56)*--(Checklist!$D$10:$D$2513=J$50)))} -> 1 | K56: {=IF($H56="","",SUMPRODUCT(--(Checklist!$E$10:$E$2513=$H56)*--(Checklist!$D$10:$D$2513=K$50)))} -> 0 | L56: {=IF($H56="","",SUMPRODUCT(--(Checklist!$E$10:$E$2513=$H56)*--(Checklist!$D$10:$D$2513=L$50)))} -> 0 | M56: {=IF($H56="","",SUMPRODUCT(--(Checklist!$E$10:$E$2513=$H56)*--(Checklist!$D$10:$D$2513=M$50)))} -> 0 | N56: =IF($H56="","",SUM(I56:M56)) -> 1
A57: F=Fulfilled | H57: Azure Cost Management | I57: {=IF($H57="","",SUMPRODUCT(--(Checklist!$E$10:$E$2513=$H57)*--(Checklist!$D$10:$D$2513=I$50)))} -> 0 | J57: {=IF($H57="","",SUMPRODUCT(--(Checklist!$E$10:$E$2513=$H57)*--(Checklist!$D$10:$D$2513=J$50)))} -> 0 | K57: {=IF($H57="","",SUMPRODUCT(--(Checklist!$E$10:$E$2513=$H57)*--(Checklist!$D$10:$D$2513=K$50)))} -> 1 | L57: {=IF($H57="","",SUMPRODUCT(--(Checklist!$E$10:$E$2513=$H57)*--(Checklist!$D$10:$D$2513=L$50)))} -> 0 | M57: {=IF($H57="","",SUMPRODUCT(--(Checklist!$E$10:$E$2513=$H57)*--(Checklist!$D$10:$D$2513=M$50)))} -> 0 | N57: =IF($H57="","",SUM(I57:M57)) -> 1
A58: NR=NotRequired | H58: Azure DevOps | I58: {=IF($H58="","",SUMPRODUCT(--(Checklist!$E$10:$E$2513=$H58)*--(Checklist!$D$10:$D$2513=I$50)))} -> 0 | J58: {=IF($H58="","",SUMPRODUCT(--(Checklist!$E$10:$E$2513=$H58)*--(Checklist!$D$10:$D$2513=J$50)))} -> 0 | K58: {=IF($H58="","",SUMPRODUCT(--(Checklist!$E$10:$E$2513=$H58)*--(Checklist!$D$10:$D$2513=K$50)))} -> 0 | L58: {=IF($H58="","",SUMPRODUCT(--(Checklist!$E$10:$E$2513=$H58)*--(Checklist!$D$10:$D$2513=L$50)))} -> 2 | M58: {=IF($H58="","",SUMPRODUCT(--(Checklist!$E$10:$E$2513=$H58)*--(Checklist!$D$10:$D$2513=M$50)))} -> 0 | N58: =IF($H58="","",SUM(I58:M58)) -> 2
A59: O=Open | H59: Azure Machine Learning | I59: {=IF($H59="","",SUMPRODUCT(--(Checklist!$E$10:$E$2513=$H59)*--(Checklist!$D$10:$D$2513=I$50)))} -> 1 | J59: {=IF($H59="","",SUMPRODUCT(--(Checklist!$E$10:$E$2513=$H59)*--(Checklist!$D$10:$D$2513=J$50)))} -> 3 | K59: {=IF($H59="","",SUMPRODUCT(--(Checklist!$E$10:$E$2513=$H59)*--(Checklist!$D$10:$D$2513=K$50)))} -> 0 | L59: {=IF($H59="","",SUMPRODUCT(--(Checklist!$E$10:$E$2513=$H59)*--(Checklist!$D$10:$D$2513=L$50)))} -> 1 | M59: {=IF($H59="","",SUMPRODUCT(--(Checklist!$E$10:$E$2513=$H59)*--(Checklist!$D$10:$D$2513=M$50)))} -> 0 | N59: =IF($H59="","",SUM(I59:M59)) -> 5
H60: Azure Monitor | I60: {=IF($H60="","",SUMPRODUCT(--(Checklist!$E$10:$E$2513=$H60)*--(Checklist!$D$10:$D$2513=I$50)))} -> 0 | J60: {=IF($H60="","",SUMPRODUCT(--(Checklist!$E$10:$E$2513=$H60)*--(Checklist!$D$10:$D$2513=J$50)))} -> 0 | K60: {=IF($H60="","",SUMPRODUCT(--(Checklist!$E$10:$E$2513=$H60)*--(Checklist!$D$10:$D$2513=K$50)))} -> 0 | L60: {=IF($H60="","",SUMPRODUCT(--(Checklist!$E$10:$E$2513=$H60)*--(Checklist!$D$10:$D$2513=L$50)))} -> 1 | M60: {=IF($H60="","",SUMPRODUCT(--(Checklist!$E$10:$E$2513=$H60)*--(Checklist!$D$10:$D$2513=M$50)))} -> 0 | N60: =IF($H60="","",SUM(I60:M60)) -> 1
H61: Azure Open AI | I61: {=IF($H61="","",SUMPRODUCT(--(Checklist!$E$10:$E$2513=$H61)*--(Checklist!$D$10:$D$2513=I$50)))} -> 1 | J61: {=IF($H61="","",SUMPRODUCT(--(Checklist!$E$10:$E$2513=$H61)*--(Checklist!$D$10:$D$2513=J$50)))} -> 1 | K61: {=IF($H61="","",SUMPRODUCT(--(Checklist!$E$10:$E$2513=$H61)*--(Checklist!$D$10:$D$2513=K$50)))} -> 0 | L61: {=IF($H61="","",SUMPRODUCT(--(Checklist!$E$10:$E$2513=$H61)*--(Checklist!$D$10:$D$2513=L$50)))} -> 0 | M61: {=IF($H61="","",SUMPRODUCT(--(Checklist!$E$10:$E$2513=$H61)*--(Checklist!$D$10:$D$2513=M$50)))} -> 0 | N61: =IF($H61="","",SUM(I61:M61)) -> 2
H62: Azure OpenAI | I62: {=IF($H62="","",SUMPRODUCT(--(Checklist!$E$10:$E$2513=$H62)*--(Checklist!$D$10:$D$2513=I$50)))} -> 10 | J62: {=IF($H62="","",SUMPRODUCT(--(Checklist!$E$10:$E$2513=$H62)*--(Checklist!$D$10:$D$2513=J$50)))} -> 34 | K62: {=IF($H62="","",SUMPRODUCT(--(Checklist!$E$10:$E$2513=$H62)*--(Checklist!$D$10:$D$2513=K$50)))} -> 17 | L62: {=IF($H62="","",SUMPRODUCT(--(Checklist!$E$10:$E$2513=$H62)*--(Checklist!$D$10:$D$2513=L$50)))} -> 27 | M62: {=IF($H62="","",SUMPRODUCT(--(Checklist!$E$10:$E$2513=$H62)*--(Checklist!$D$10:$D$2513=M$50)))} -> 8 | N62: =IF($H62="","",SUM(I62:M62)) -> 96
H63: Azure RBAC | I63: {=IF($H63="","",SUMPRODUCT(--(Checklist!$E$10:$E$2513=$H63)*--(Checklist!$D$10:$D$2513=I$50)))} -> 0 | J63: {=IF($H63="","",SUMPRODUCT(--(Checklist!$E$10:$E$2513=$H63)*--(Checklist!$D$10:$D$2513=J$50)))} -> 1 | K63: {=IF($H63="","",SUMPRODUCT(--(Checklist!$E$10:$E$2513=$H63)*--(Checklist!$D$10:$D$2513=K$50)))} -> 0 | L63: {=IF($H63="","",SUMPRODUCT(--(Checklist!$E$10:$E$2513=$H63)*--(Checklist!$D$10:$D$2513=L$50)))} -> 0 | M63: {=IF($H63="","",SUMPRODUCT(--(Checklist!$E$10:$E$2513=$H63)*--(Checklist!$D$10:$D$2513=M$50)))} -> 0 | N63: =IF($H63="","",SUM(I63:M63)) -> 1
H64: Azure Resource Manager | I64: {=IF($H64="","",SUMPRODUCT(--(Checklist!$E$10:$E$2513=$H64)*--(Checklist!$D$10:$D$2513=I$50)))} -> 0 | J64: {=IF($H64="","",SUMPRODUCT(--(Checklist!$E$10:$E$2513=$H64)*--(Checklist!$D$10:$D$2513=J$50)))} -> 0 | K64: {=IF($H64="","",SUMPRODUCT(--(Checklist!$E$10:$E$2513=$H64)*--(Checklist!$D$10:$D$2513=K$50)))} -> 0 | L64: {=IF($H64="","",SUMPRODUCT(--(Checklist!$E$10:$E$2513=$H64)*--(Checklist!$D$10:$D$2513=L$50)))} -> 1 | M64: {=IF($H64="","",SUMPRODUCT(--(Checklist!$E$10:$E$2513=$H64)*--(Checklist!$D$10:$D$2513=M$50)))} -> 0 | N64: =IF($H64="","",SUM(I64:M64)) -> 1
H65: Azure Service Health | I65: {=IF($H65="","",SUMPRODUCT(--(Checklist!$E$10:$E$2513=$H65)*--(Checklist!$D$10:$D$2513=I$50)))} -> 0 | J65: {=IF($H65="","",SUMPRODUCT(--(Checklist!$E$10:$E$2513=$H65)*--(Checklist!$D$10:$D$2513=J$50)))} -> 0 | K65: {=IF($H65="","",SUMPRODUCT(--(Checklist!$E$10:$E$2513=$H65)*--(Checklist!$D$10:$D$2513=K$50)))} -> 0 | L65: {=IF($H65="","",SUMPRODUCT(--(Checklist!$E$10:$E$2513=$H65)*--(Checklist!$D$10:$D$2513=L$50)))} -> 1 | M65: {=IF($H65="","",SUMPRODUCT(--(Checklist!$E$10:$E$2513=$H65)*--(Checklist!$D$10:$D$2513=M$50)))} -> 0 | N65: =IF($H65="","",SUM(I65:M65)) -> 1
H66: Cognitive Search | I66: {=IF($H66="","",SUMPRODUCT(--(Checklist!$E$10:$E$2513=$H66)*--(Checklist!$D$10:$D$2513=I$50)))} -> 7 | J66: {=IF($H66="","",SUMPRODUCT(--(Checklist!$E$10:$E$2513=$H66)*--(Checklist!$D$10:$D$2513=J$50)))} -> 0 | K66: {=IF($H66="","",SUMPRODUCT(--(Checklist!$E$10:$E$2513=$H66)*--(Checklist!$D$10:$D$2513=K$50)))} -> 0 | L66: {=IF($H66="","",SUMPRODUCT(--(Checklist!$E$10:$E$2513=$H66)*--(Checklist!$D$10:$D$2513=L$50)))} -> 0 | M66: {=IF($H66="","",SUMPRODUCT(--(Checklist!$E$10:$E$2513=$H66)*--(Checklist!$D$10:$D$2513=M$50)))} -> 0 | N66: =IF($H66="","",SUM(I66:M66)) -> 7
H67: Cognitive Services | I67: {=IF($H67="","",SUMPRODUCT(--(Checklist!$E$10:$E$2513=$H67)*--(Checklist!$D$10:$D$2513=I$50)))} -> 6 | J67: {=IF($H67="","",SUMPRODUCT(--(Checklist!$E$10:$E$2513=$H67)*--(Checklist!$D$10:$D$2513=J$50)))} -> 0 | K67: {=IF($H67="","",SUMPRODUCT(--(Checklist!$E$10:$E$2513=$H67)*--(Checklist!$D$10:$D$2513=K$50)))} -> 0 | L67: {=IF($H67="","",SUMPRODUCT(--(Checklist!$E$10:$E$2513=$H67)*--(Checklist!$D$10:$D$2513=L$50)))} -> 0 | M67: {=IF($H67="","",SUMPRODUCT(--(Checklist!$E$10:$E$2513=$H67)*--(Checklist!$D$10:$D$2513=M$50)))} -> 0 | N67: =IF($H67="","",SUM(I67:M67)) -> 6
H68: Microsoft cloud security benchmark | I68: {=IF($H68="","",SUMPRODUCT(--(Checklist!$E$10:$E$2513=$H68)*--(Checklist!$D$10:$D$2513=I$50)))} -> 0 | J68: {=IF($H68="","",SUMPRODUCT(--(Checklist!$E$10:$E$2513=$H68)*--(Checklist!$D$10:$D$2513=J$50)))} -> 0 | K68: {=IF($H68="","",SUMPRODUCT(--(Checklist!$E$10:$E$2513=$H68)*--(Checklist!$D$10:$D$2513=K$50)))} -> 0 | L68: {=IF($H68="","",SUMPRODUCT(--(Checklist!$E$10:$E$2513=$H68)*--(Checklist!$D$10:$D$2513=L$50)))} -> 1 | M68: {=IF($H68="","",SUMPRODUCT(--(Checklist!$E$10:$E$2513=$H68)*--(Checklist!$D$10:$D$2513=M$50)))} -> 0 | N68: =IF($H68="","",SUM(I68:M68)) -> 1
H69: Microsoft Defender for Cloud | I69: {=IF($H69="","",SUMPRODUCT(--(Checklist!$E$10:$E$2513=$H69)*--(Checklist!$D$10:$D$2513=I$50)))} -> 0 | J69: {=IF($H69="","",SUMPRODUCT(--(Checklist!$E$10:$E$2513=$H69)*--(Checklist!$D$10:$D$2513=J$50)))} -> 3 | K69: {=IF($H69="","",SUMPRODUCT(--(Checklist!$E$10:$E$2513=$H69)*--(Checklist!$D$10:$D$2513=K$50)))} -> 0 | L69: {=IF($H69="","",SUMPRODUCT(--(Checklist!$E$10:$E$2513=$H69)*--(Checklist!$D$10:$D$2513=L$50)))} -> 0 | M69: {=IF($H69="","",SUMPRODUCT(--(Checklist!$E$10:$E$2513=$H69)*--(Checklist!$D$10:$D$2513=M$50)))} -> 0 | N69: =IF($H69="","",SUM(I69:M69)) -> 3
H70: Microsoft Entra | I70: {=IF($H70="","",SUMPRODUCT(--(Checklist!$E$10:$E$2513=$H70)*--(Checklist!$D$10:$D$2513=I$50)))} -> 0 | J70: {=IF($H70="","",SUMPRODUCT(--(Checklist!$E$10:$E$2513=$H70)*--(Checklist!$D$10:$D$2513=J$50)))} -> 4 | K70: {=IF($H70="","",SUMPRODUCT(--(Checklist!$E$10:$E$2513=$H70)*--(Checklist!$D$10:$D$2513=K$50)))} -> 0 | L70: {=IF($H70="","",SUMPRODUCT(--(Checklist!$E$10:$E$2513=$H70)*--(Checklist!$D$10:$D$2513=L$50)))} -> 0 | M70: {=IF($H70="","",SUMPRODUCT(--(Checklist!$E$10:$E$2513=$H70)*--(Checklist!$D$10:$D$2513=M$50)))} -> 0 | N70: =IF($H70="","",SUM(I70:M70)) -> 4
H71: Microsoft Purview | I71: {=IF($H71="","",SUMPRODUCT(--(Checklist!$E$10:$E$2513=$H71)*--(Checklist!$D$10:$D$2513=I$50)))} -> 0 | J71: {=IF($H71="","",SUMPRODUCT(--(Checklist!$E$10:$E$2513=$H71)*--(Checklist!$D$10:$D$2513=J$50)))} -> 3 | K71: {=IF($H71="","",SUMPRODUCT(--(Checklist!$E$10:$E$2513=$H71)*--(Checklist!$D$10:$D$2513=K$50)))} -> 0 | L71: {=IF($H71="","",SUMPRODUCT(--(Checklist!$E$10:$E$2513=$H71)*--(Checklist!$D$10:$D$2513=L$50)))} -> 0 | M71: {=IF($H71="","",SUMPRODUCT(--(Checklist!$E$10:$E$2513=$H71)*--(Checklist!$D$10:$D$2513=M$50)))} -> 0 | N71: =IF($H71="","",SUM(I71:M71)) -> 3
... H73: NA | I73: {=IF($H73="","",SUMPRODUCT(--(Checklist!$E$10:$E$2513=$H73)*--(Checklist!$D$10:$D$2513=I$50)))} -> 0 | J73: {=IF($H73="","",SUMPRODUCT(--(Checklist!$E$10:$E$2513=$H73)*--(Checklist!$D$10:$D$2513=J$50)))} -> 11 | K73: {=IF($H73="","",SUMPRODUCT(--(Checklist!$E$10:$E$2513=$H73)*--(Checklist!$D$10:$D$2513=K$50)))} -> 1 | L73: {=IF($H73="","",SUMPRODUCT(--(Checklist!$E$10:$E$2513=$H73)*--(Checklist!$D$10:$D$2513=L$50)))} -> 2 | M73: {=IF($H73="","",SUMPRODUCT(--(Checklist!$E$10:$E$2513=$H73)*--(Checklist!$D$10:$D$2513=M$50)))} -> 0 | N73: =IF($H73="","",SUM(I73:M73)) -> 14
I74: {=IF($H74="","",SUMPRODUCT(--(Checklist!$E$10:$E$2513=$H74)*--(Checklist!$D$10:$D$2513=I$50)))} | J74: {=IF($H74="","",SUMPRODUCT(--(Checklist!$E$10:$E$2513=$H74)*--(Checklist!$D$10:$D$2513=J$50)))} | K74: {=IF($H74="","",SUMPRODUCT(--(Checklist!$E$10:$E$2513=$H74)*--(Checklist!$D$10:$D$2513=K$50)))} | L74: {=IF($H74="","",SUMPRODUCT(--(Checklist!$E$10:$E$2513=$H74)*--(Checklist!$D$10:$D$2513=L$50)))} | M74: {=IF($H74="","",SUMPRODUCT(--(Checklist!$E$10:$E$2513=$H74)*--(Checklist!$D$10:$D$2513=M$50)))} | N74: =IF($H74="","",SUM(I74:M74)) | Z74: Checks with ARG query
I75: {=IF($H75="","",SUMPRODUCT(--(Checklist!$E$10:$E$2513=$H75)*--(Checklist!$D$10:$D$2513=I$50)))} | J75: {=IF($H75="","",SUMPRODUCT(--(Checklist!$E$10:$E$2513=$H75)*--(Checklist!$D$10:$D$2513=J$50)))} | K75: {=IF($H75="","",SUMPRODUCT(--(Checklist!$E$10:$E$2513=$H75)*--(Checklist!$D$10:$D$2513=K$50)))} | L75: {=IF($H75="","",SUMPRODUCT(--(Checklist!$E$10:$E$2513=$H75)*--(Checklist!$D$10:$D$2513=L$50)))} | M75: {=IF($H75="","",SUMPRODUCT(--(Checklist!$E$10:$E$2513=$H75)*--(Checklist!$D$10:$D$2513=M$50)))} | N75: =IF($H75="","",SUM(I75:M75)) | Y75: =Values!$L$2 -> Reliability | Z75: =COUNTIFS(Checklist!$D$10:$D$487, Y75, Checklist!$N$10:$N$487, "<>") -> 1
I76: {=IF($H76="","",SUMPRODUCT(--(Checklist!$E$10:$E$2513=$H76)*--(Checklist!$D$10:$D$2513=I$50)))} | J76: {=IF($H76="","",SUMPRODUCT(--(Checklist!$E$10:$E$2513=$H76)*--(Checklist!$D$10:$D$2513=J$50)))} | K76: {=IF($H76="","",SUMPRODUCT(--(Checklist!$E$10:$E$2513=$H76)*--(Checklist!$D$10:$D$2513=K$50)))} | L76: {=IF($H76="","",SUMPRODUCT(--(Checklist!$E$10:$E$2513=$H76)*--(Checklist!$D$10:$D$2513=L$50)))} | M76: {=IF($H76="","",SUMPRODUCT(--(Checklist!$E$10:$E$2513=$H76)*--(Checklist!$D$10:$D$2513=M$50)))} | N76: =IF($H76="","",SUM(I76:M76)) | Y76: =Values!$L$3 -> Security | Z76: =COUNTIFS(Checklist!$D$10:$D$487, Y76, Checklist!$N$10:$N$487, "<>") -> 4
I77: {=IF($H77="","",SUMPRODUCT(--(Checklist!$E$10:$E$2513=$H77)*--(Checklist!$D$10:$D$2513=I$50)))} | J77: {=IF($H77="","",SUMPRODUCT(--(Checklist!$E$10:$E$2513=$H77)*--(Checklist!$D$10:$D$2513=J$50)))} | K77: {=IF($H77="","",SUMPRODUCT(--(Checklist!$E$10:$E$2513=$H77)*--(Checklist!$D$10:$D$2513=K$50)))} | L77: {=IF($H77="","",SUMPRODUCT(--(Checklist!$E$10:$E$2513=$H77)*--(Checklist!$D$10:$D$2513=L$50)))} | M77: {=IF($H77="","",SUMPRODUCT(--(Checklist!$E$10:$E$2513=$H77)*--(Checklist!$D$10:$D$2513=M$50)))} | N77: =IF($H77="","",SUM(I77:M77)) | Y77: =Values!$L$4 -> Cost | Z77: =COUNTIFS(Checklist!$D$10:$D$487, Y77, Checklist!$N$10:$N$487, "<>") -> 0
I78: {=IF($H78="","",SUMPRODUCT(--(Checklist!$E$10:$E$2513=$H78)*--(Checklist!$D$10:$D$2513=I$50)))} | J78: {=IF($H78="","",SUMPRODUCT(--(Checklist!$E$10:$E$2513=$H78)*--(Checklist!$D$10:$D$2513=J$50)))} | K78: {=IF($H78="","",SUMPRODUCT(--(Checklist!$E$10:$E$2513=$H78)*--(Checklist!$D$10:$D$2513=K$50)))} | L78: {=IF($H78="","",SUMPRODUCT(--(Checklist!$E$10:$E$2513=$H78)*--(Checklist!$D$10:$D$2513=L$50)))} | M78: {=IF($H78="","",SUMPRODUCT(--(Checklist!$E$10:$E$2513=$H78)*--(Checklist!$D$10:$D$2513=M$50)))} | N78: =IF($H78="","",SUM(I78:M78)) | Y78: =Values!$L$5 -> Operations | Z78: =COUNTIFS(Checklist!$D$10:$D$487, Y78, Checklist!$N$10:$N$487, "<>") -> 2
I79: {=IF($H79="","",SUMPRODUCT(--(Checklist!$E$10:$E$2513=$H79)*--(Checklist!$D$10:$D$2513=I$50)))} | J79: {=IF($H79="","",SUMPRODUCT(--(Checklist!$E$10:$E$2513=$H79)*--(Checklist!$D$10:$D$2513=J$50)))} | K79: {=IF($H79="","",SUMPRODUCT(--(Checklist!$E$10:$E$2513=$H79)*--(Checklist!$D$10:$D$2513=K$50)))} | L79: {=IF($H79="","",SUMPRODUCT(--(Checklist!$E$10:$E$2513=$H79)*--(Checklist!$D$10:$D$2513=L$50)))} | M79: {=IF($H79="","",SUMPRODUCT(--(Checklist!$E$10:$E$2513=$H79)*--(Checklist!$D$10:$D$2513=M$50)))} | N79: =IF($H79="","",SUM(I79:M79)) | Y79: =Values!$L$6 -> Performance | Z79: =COUNTIFS(Checklist!$D$10:$D$487, Y79, Checklist!$N$10:$N$487, "<>") -> 0
I80: {=IF($H80="","",SUMPRODUCT(--(Checklist!$E$10:$E$2513=$H80)*--(Checklist!$D$10:$D$2513=I$50)))} | J80: {=IF($H80="","",SUMPRODUCT(--(Checklist!$E$10:$E$2513=$H80)*--(Checklist!$D$10:$D$2513=J$50)))} | K80: {=IF($H80="","",SUMPRODUCT(--(Checklist!$E$10:$E$2513=$H80)*--(Checklist!$D$10:$D$2513=K$50)))} | L80: {=IF($H80="","",SUMPRODUCT(--(Checklist!$E$10:$E$2513=$H80)*--(Checklist!$D$10:$D$2513=L$50)))} | M80: {=IF($H80="","",SUMPRODUCT(--(Checklist!$E$10:$E$2513=$H80)*--(Checklist!$D$10:$D$2513=M$50)))} | N80: =IF($H80="","",SUM(I80:M80)) | Z80: =SUM(Z75:Z79) -> 7
I81: {=IF($H81="","",SUMPRODUCT(--(Checklist!$E$10:$E$2513=$H81)*--(Checklist!$D$10:$D$2513=I$50)))} | J81: {=IF($H81="","",SUMPRODUCT(--(Checklist!$E$10:$E$2513=$H81)*--(Checklist!$D$10:$D$2513=J$50)))} | K81: {=IF($H81="","",SUMPRODUCT(--(Checklist!$E$10:$E$2513=$H81)*--(Checklist!$D$10:$D$2513=K$50)))} | L81: {=IF($H81="","",SUMPRODUCT(--(Checklist!$E$10:$E$2513=$H81)*--(Checklist!$D$10:$D$2513=L$50)))} | M81: {=IF($H81="","",SUMPRODUCT(--(Checklist!$E$10:$E$2513=$H81)*--(Checklist!$D$10:$D$2513=M$50)))} | N81: =IF($H81="","",SUM(I81:M81))
I82: {=IF($H82="","",SUMPRODUCT(--(Checklist!$E$10:$E$2513=$H82)*--(Checklist!$D$10:$D$2513=I$50)))} | J82: {=IF($H82="","",SUMPRODUCT(--(Checklist!$E$10:$E$2513=$H82)*--(Checklist!$D$10:$D$2513=J$50)))} | K82: {=IF($H82="","",SUMPRODUCT(--(Checklist!$E$10:$E$2513=$H82)*--(Checklist!$D$10:$D$2513=K$50)))} | L82: {=IF($H82="","",SUMPRODUCT(--(Checklist!$E$10:$E$2513=$H82)*--(Checklist!$D$10:$D$2513=L$50)))} | M82: {=IF($H82="","",SUMPRODUCT(--(Checklist!$E$10:$E$2513=$H82)*--(Checklist!$D$10:$D$2513=M$50)))} | N82: =IF($H82="","",SUM(I82:M82))
I83: {=IF($H83="","",SUMPRODUCT(--(Checklist!$E$10:$E$2513=$H83)*--(Checklist!$D$10:$D$2513=I$50)))} | J83: {=IF($H83="","",SUMPRODUCT(--(Checklist!$E$10:$E$2513=$H83)*--(Checklist!$D$10:$D$2513=J$50)))} | K83: {=IF($H83="","",SUMPRODUCT(--(Checklist!$E$10:$E$2513=$H83)*--(Checklist!$D$10:$D$2513=K$50)))} | L83: {=IF($H83="","",SUMPRODUCT(--(Checklist!$E$10:$E$2513=$H83)*--(Checklist!$D$10:$D$2513=L$50)))} | M83: {=IF($H83="","",SUMPRODUCT(--(Checklist!$E$10:$E$2513=$H83)*--(Checklist!$D$10:$D$2513=M$50)))} | N83: =IF($H83="","",SUM(I83:M83))
I84: {=IF($H84="","",SUMPRODUCT(--(Checklist!$E$10:$E$2513=$H84)*--(Checklist!$D$10:$D$2513=I$50)))} | J84: {=IF($H84="","",SUMPRODUCT(--(Checklist!$E$10:$E$2513=$H84)*--(Checklist!$D$10:$D$2513=J$50)))} | K84: {=IF($H84="","",SUMPRODUCT(--(Checklist!$E$10:$E$2513=$H84)*--(Checklist!$D$10:$D$2513=K$50)))} | L84: {=IF($H84="","",SUMPRODUCT(--(Checklist!$E$10:$E$2513=$H84)*--(Checklist!$D$10:$D$2513=L$50)))} | M84: {=IF($H84="","",SUMPRODUCT(--(Checklist!$E$10:$E$2513=$H84)*--(Checklist!$D$10:$D$2513=M$50)))} | N84: =IF($H84="","",SUM(I84:M84))
I85: {=IF($H85="","",SUMPRODUCT(--(Checklist!$E$10:$E$2513=$H85)*--(Checklist!$D$10:$D$2513=I$50)))} | J85: {=IF($H85="","",SUMPRODUCT(--(Checklist!$E$10:$E$2513=$H85)*--(Checklist!$D$10:$D$2513=J$50)))} | K85: {=IF($H85="","",SUMPRODUCT(--(Checklist!$E$10:$E$2513=$H85)*--(Checklist!$D$10:$D$2513=K$50)))} | L85: {=IF($H85="","",SUMPRODUCT(--(Checklist!$E$10:$E$2513=$H85)*--(Checklist!$D$10:$D$2513=L$50)))} | M85: {=IF($H85="","",SUMPRODUCT(--(Checklist!$E$10:$E$2513=$H85)*--(Checklist!$D$10:$D$2513=M$50)))} | N85: =IF($H85="","",SUM(I85:M85))
I86: {=IF($H86="","",SUMPRODUCT(--(Checklist!$E$10:$E$2513=$H86)*--(Checklist!$D$10:$D$2513=I$50)))} | J86: {=IF($H86="","",SUMPRODUCT(--(Checklist!$E$10:$E$2513=$H86)*--(Checklist!$D$10:$D$2513=J$50)))} | K86: {=IF($H86="","",SUMPRODUCT(--(Checklist!$E$10:$E$2513=$H86)*--(Checklist!$D$10:$D$2513=K$50)))} | L86: {=IF($H86="","",SUMPRODUCT(--(Checklist!$E$10:$E$2513=$H86)*--(Checklist!$D$10:$D$2513=L$50)))} | M86: {=IF($H86="","",SUMPRODUCT(--(Checklist!$E$10:$E$2513=$H86)*--(Checklist!$D$10:$D$2513=M$50)))} | N86: =IF($H86="","",SUM(I86:M86))
I87: {=IF($H87="","",SUMPRODUCT(--(Checklist!$E$10:$E$2513=$H87)*--(Checklist!$D$10:$D$2513=I$50)))} | J87: {=IF($H87="","",SUMPRODUCT(--(Checklist!$E$10:$E$2513=$H87)*--(Checklist!$D$10:$D$2513=J$50)))} | K87: {=IF($H87="","",SUMPRODUCT(--(Checklist!$E$10:$E$2513=$H87)*--(Checklist!$D$10:$D$2513=K$50)))} | L87: {=IF($H87="","",SUMPRODUCT(--(Checklist!$E$10:$E$2513=$H87)*--(Checklist!$D$10:$D$2513=L$50)))} | M87: {=IF($H87="","",SUMPRODUCT(--(Checklist!$E$10:$E$2513=$H87)*--(Checklist!$D$10:$D$2513=M$50)))} | N87: =IF($H87="","",SUM(I87:M87))
I88: {=IF($H88="","",SUMPRODUCT(--(Checklist!$E$10:$E$2513=$H88)*--(Checklist!$D$10:$D$2513=I$50)))} | J88: {=IF($H88="","",SUMPRODUCT(--(Checklist!$E$10:$E$2513=$H88)*--(Checklist!$D$10:$D$2513=J$50)))} | K88: {=IF($H88="","",SUMPRODUCT(--(Checklist!$E$10:$E$2513=$H88)*--(Checklist!$D$10:$D$2513=K$50)))} | L88: {=IF($H88="","",SUMPRODUCT(--(Checklist!$E$10:$E$2513=$H88)*--(Checklist!$D$10:$D$2513=L$50)))} | M88: {=IF($H88="","",SUMPRODUCT(--(Checklist!$E$10:$E$2513=$H88)*--(Checklist!$D$10:$D$2513=M$50)))} | N88: =IF($H88="","",SUM(I88:M88))
I89: {=IF($H89="","",SUMPRODUCT(--(Checklist!$E$10:$E$2513=$H89)*--(Checklist!$D$10:$D$2513=I$50)))} | J89: {=IF($H89="","",SUMPRODUCT(--(Checklist!$E$10:$E$2513=$H89)*--(Checklist!$D$10:$D$2513=J$50)))} | K89: {=IF($H89="","",SUMPRODUCT(--(Checklist!$E$10:$E$2513=$H89)*--(Checklist!$D$10:$D$2513=K$50)))} | L89: {=IF($H89="","",SUMPRODUCT(--(Checklist!$E$10:$E$2513=$H89)*--(Checklist!$D$10:$D$2513=L$50)))} | M89: {=IF($H89="","",SUMPRODUCT(--(Checklist!$E$10:$E$2513=$H89)*--(Checklist!$D$10:$D$2513=M$50)))} | N89: =IF($H89="","",SUM(I89:M89))
I90: {=IF($H90="","",SUMPRODUCT(--(Checklist!$E$10:$E$2513=$H90)*--(Checklist!$D$10:$D$2513=I$50)))} | J90: {=IF($H90="","",SUMPRODUCT(--(Checklist!$E$10:$E$2513=$H90)*--(Checklist!$D$10:$D$2513=J$50)))} | K90: {=IF($H90="","",SUMPRODUCT(--(Checklist!$E$10:$E$2513=$H90)*--(Checklist!$D$10:$D$2513=K$50)))} | L90: {=IF($H90="","",SUMPRODUCT(--(Checklist!$E$10:$E$2513=$H90)*--(Checklist!$D$10:$D$2513=L$50)))} | M90: {=IF($H90="","",SUMPRODUCT(--(Checklist!$E$10:$E$2513=$H90)*--(Checklist!$D$10:$D$2513=M$50)))} | N90: =IF($H90="","",SUM(I90:M90))
I91: {=IF($H91="","",SUMPRODUCT(--(Checklist!$E$10:$E$2513=$H91)*--(Checklist!$D$10:$D$2513=I$50)))} | J91: {=IF($H91="","",SUMPRODUCT(--(Checklist!$E$10:$E$2513=$H91)*--(Checklist!$D$10:$D$2513=J$50)))} | K91: {=IF($H91="","",SUMPRODUCT(--(Checklist!$E$10:$E$2513=$H91)*--(Checklist!$D$10:$D$2513=K$50)))} | L91: {=IF($H91="","",SUMPRODUCT(--(Checklist!$E$10:$E$2513=$H91)*--(Checklist!$D$10:$D$2513=L$50)))} | M91: {=IF($H91="","",SUMPRODUCT(--(Checklist!$E$10:$E$2513=$H91)*--(Checklist!$D$10:$D$2513=M$50)))} | N91: =IF($H91="","",SUM(I91:M91))
I92: {=IF($H92="","",SUMPRODUCT(--(Checklist!$E$10:$E$2513=$H92)*--(Checklist!$D$10:$D$2513=I$50)))} | J92: {=IF($H92="","",SUMPRODUCT(--(Checklist!$E$10:$E$2513=$H92)*--(Checklist!$D$10:$D$2513=J$50)))} | K92: {=IF($H92="","",SUMPRODUCT(--(Checklist!$E$10:$E$2513=$H92)*--(Checklist!$D$10:$D$2513=K$50)))} | L92: {=IF($H92="","",SUMPRODUCT(--(Checklist!$E$10:$E$2513=$H92)*--(Checklist!$D$10:$D$2513=L$50)))} | M92: {=IF($H92="","",SUMPRODUCT(--(Checklist!$E$10:$E$2513=$H92)*--(Checklist!$D$10:$D$2513=M$50)))} | N92: =IF($H92="","",SUM(I92:M92))
... I122: {=IF($H122="","",SUMPRODUCT(--(Checklist!$E$10:$E$2513=$H122)*--(Checklist!$D$10:$D$2513=I$50)))} | J122: {=IF($H122="","",SUMPRODUCT(--(Checklist!$E$10:$E$2513=$H122)*--(Checklist!$D$10:$D$2513=J$50)))} | K122: {=IF($H122="","",SUMPRODUCT(--(Checklist!$E$10:$E$2513=$H122)*--(Checklist!$D$10:$D$2513=K$50)))} | L122: {=IF($H122="","",SUMPRODUCT(--(Checklist!$E$10:$E$2513=$H122)*--(Checklist!$D$10:$D$2513=L$50)))} | M122: {=IF($H122="","",SUMPRODUCT(--(Checklist!$E$10:$E$2513=$H122)*--(Checklist!$D$10:$D$2513=M$50)))} | N122: =IF($H122="","",SUM(I122:M122))
H123: =COUNTA(H51:H122) -> 23 | I123: =SUM(I51:I122) -> 26 | J123: =SUM(J51:J122) -> 77 | K123: =SUM(K51:K122) -> 20 | L123: =SUM(L51:L122) -> 43 | M123: =SUM(M51:M122) -> 11 | N123: =SUM(N51:N122) -> 177

Sheet Values
A1: Severity | B1: Status | C1: Category | D1: Reference checklist base URL | E1: Default title | F1: Technologies | G1: Technology file prefix | H1: Folder | I1: Languages | J1: Status descriptions | K1: Language file suffix | L1: WAF Pillars | M1: YesNo | N1: Settings | O1: Setting Value | P1: Setting Format | Q1: Services | R1: Sources | S1: Views
A2: High | B2: Not verified | C2: Identity and Access Management | D2: https://raw.githubusercontent.com/Azure/review-checklists/main/ | E2: Use the "Import latest checklist" button to get the latest version of a review checklist | F2: {=_xlfn._xlws.FILTER(ChecklistIndex!B1:D52,ChecklistIndex!A1:A52=Checklist!G5)} -> Azure Landing Zone | G2: alz | H2: checklists | I2: English | J2: This check has not been looked at yet | K2: en | L2: Reliability | M2: Yes | N2: Telemetry | O2: =IF(Checklist!F4=Values!M3,"no","yes") -> yes | P2: yes/no | Q2: {=_xlfn._xlws.SORT(_xlfn.UNIQUE(_xlfn._xlws.FILTER(Checklist!$E$10:$E$2513, Checklist!$E$10:$E$2513<>"")))} -> Azure AI Content Safety | R2: Review checklists | S2: all
A3: Medium | B3: Open | C3: Network Topology and Connectivity | F3: AI Landing Zone | G3: ai_lz | H3: checklists | I3: Japanese | J3: There is an action item associated to this check | K3: ja | L3: Security | M3: No | N3: Telemetry confirmation | O3: no | P3: yes/no | Q3: Azure AI Foundry | R3: WAF service guides | S3: normal
A4: Low | B4: Fulfilled | C4: BC and DR | F4: WAF | G4: waf | H4: checklists | I4: Korean | J4: This check has been verified, and there are no further action items associated to it | K4: ko | L4: Cost | Q4: Azure AI Search | R4: the-aks-checklist.com | S4: waf
B5: Not required | C5: Governance and Security | F5: AKS | G5: aks | H5: checklists | I5: Brazilian Portuguese | J5: Recommendation understood, but not needed by current requirements | K5: pt | L5: Operations | Q5: Azure AI Services | R5: APRL | S5: alz
B6: N/A | C6: Cost Governance | F6: AVD | G6: avd | H6: checklists | I6: Spanish | J6: Not applicable for current design | K6: es | L6: Performance | Q6: Azure API Management | R6: Multiple
C7: Operations | F7: AVS Design | G7: avs | H7: checklists | I7: Chinese Traditional | K7: zh-Hant | Q7: Azure Container Apps
C8: Application Deployment | F8: AVS Implementation | G8: avs_implementation | H8: checklists | Q8: Azure Cost Management
F9: Multitenancy | G9: multitenancy | H9: checklists | Q9: Azure DevOps
F10: Network App Delivery | G10: network_appdelivery | H10: checklists | Q10: Azure Machine Learning
F11: SAP | G11: sap | H11: checklists | Q11: Azure Monitor
F12: API Management | G12: apim | H12: checklists | Q12: Azure Open AI
F13: Cost Optimization | G13: cost | H13: checklists | Q13: Azure OpenAI
F14: ARO | G14: aro | H14: checklists | Q14: Azure RBAC
F15: Spring Apps | G15: azurespringapps | H15: checklists | Q15: Azure Resource Manager
F16: Front Door | G16: afd | H16: checklists | Q16: Azure Service Health
F17: Azure Devops | G17: ado | H17: checklists | Q17: Cognitive Search
F18: Azure Arc | G18: azure_arc | H18: checklists | Q18: Cognitive Services
F19: SQL Migration | G19: sql | H19: checklists | Q19: Microsoft cloud security benchmark
Q20: Microsoft Defender for Cloud
Q21: Microsoft Entra
Q22: Microsoft Purview
Q23: Microsoft Threat Modeling Tool
Q24: NA

Sheet ChecklistIndex
A1: Source | B1: Name | C1: File prefix | D1: Folder | E1: View
A2: Review checklists | B2: Azure Landing Zone | C2: alz | D2: checklists | E2: alz
A3: Review checklists | B3: AI Landing Zone | C3: ai_lz | D3: checklists | E3: normal
A4: Review checklists | B4: WAF | C4: waf | D4: checklists | E4: waf
A5: Review checklists | B5: AKS | C5: aks | D5: checklists | E5: normal
A6: Review checklists | B6: AVD | C6: avd | D6: checklists | E6: normal
A7: Review checklists | B7: AVS Design | C7: avs | D7: checklists | E7: normal
A8: Review checklists | B8: AVS Implementation | C8: avs_implementation | D8: checklists | E8: normal
A9: Review checklists | B9: Multitenancy | C9: multitenancy | D9: checklists | E9: normal
A10: Review checklists | B10: Network App Delivery | C10: network_appdelivery | D10: checklists | E10: normal
A11: Review checklists | B11: SAP | C11: sap | D11: checklists | E11: normal
A12: Review checklists | B12: API Management | C12: apim | D12: checklists | E12: normal
... A34: Multiple | B34: Review + APRL + SG | C34: fullwaf | D34: checklists-ext | E34: waf

Sheet ARG
A2: Date run:
A3: Subscription(s):
A4: Mgmt group(s):
A5: Result limit: | C5: 100
A7: Rec ID | B7: Rec GUID | C7: Resource | D7: Subscription | E7: RG | F7: Provider | G7: Type | H7: Name | I7: Compliant
A1240: G02.02 | B1240: a0477a20-9945-4bda-9333-4f2491163418
A1241: G02.02 | B1241: a0477a20-9945-4bda-9333-4f2491163418 | C1241: /subscriptions/3e78e84b-6750-44b9-9d57-d9bba935237a/resourceGroups/keyvault/providers/Microsoft.KeyVault/vaults/cloudtrooper | D1241: 3e78e84b-6750-44b9-9d57-d9bba935237a | E1241: keyvault | F1241: Microsoft.KeyVault | G1241: vaults | H1241: cloudtrooper | I1241: Fail
A1242: G02.02 | B1242: a0477a20-9945-4bda-9333-4f2491163418 | C1242: /subscriptions/e7da9914-9b05-4891-893c-546cb7b0422e/resourceGroups/argtest/providers/Microsoft.KeyVault/vaults/jomore-nopurgeprotection | D1242: e7da9914-9b05-4891-893c-546cb7b0422e | E1242: argtest | F1242: Microsoft.KeyVault | G1242: vaults | H1242: jomore-nopurgeprotection
A1243: G02.02 | B1243: a0477a20-9945-4bda-9333-4f2491163418 | C1243: /subscriptions/e7da9914-9b05-4891-893c-546cb7b0422e/resourceGroups/argtest/providers/Microsoft.KeyVault/vaults/jomore-purgeprotection | D1243: e7da9914-9b05-4891-893c-546cb7b0422e | E1243: argtest | F1243: Microsoft.KeyVault | G1243: vaults | H1243: jomore-purgeprotection
A1244: G02.02 | B1244: a0477a20-9945-4bda-9333-4f2491163418 | C1244: /subscriptions/e7da9914-9b05-4891-893c-546cb7b0422e/resourceGroups/fta/providers/Microsoft.KeyVault/vaults/keyvaultfta | D1244: e7da9914-9b05-4891-893c-546cb7b0422e | E1244: fta | F1244: Microsoft.KeyVault | G1244: vaults | H1244: keyvaultfta
A1245: G02.02 | B1245: a0477a20-9945-4bda-9333-4f2491163418 | C1245: /subscriptions/e7da9914-9b05-4891-893c-546cb7b0422e/resourceGroups/keyvaults/providers/Microsoft.KeyVault/vaults/joseakv-airs | D1245: e7da9914-9b05-4891-893c-546cb7b0422e | E1245: keyvaults | F1245: Microsoft.KeyVault | G1245: vaults | H1245: joseakv-airs
A1246: G02.02 | B1246: a0477a20-9945-4bda-9333-4f2491163418 | C1246: /subscriptions/e7da9914-9b05-4891-893c-546cb7b0422e/resourceGroups/myKeyvault/providers/Microsoft.KeyVault/vaults/erjositoKeyvault | D1246: e7da9914-9b05-4891-893c-546cb7b0422e | E1246: myKeyvault | F1246: Microsoft.KeyVault | G1246: vaults | H1246: erjositoKeyvault
